rtl/memory/data_ram.sv
import riscv_pkg::*;

module data_ram #(
    parameter int XLEN        = 32,
    parameter int DEPTH_WORDS = 1024
) (
    input logic clk,
    input logic write_enable,
    input logic [XLEN-1:0] address,
    input logic [XLEN-1:0] write_data,
    output logic [XLEN-1:0] read_data
);

    logic [XLEN-1:0] memory[DEPTH_WORDS];
    logic [$clog2(DEPTH_WORDS)-1:0] word_address;

    assign word_address = address / INSTRUCTION_BYTES;

    /*
    * Asynchronous read
    */
    assign read_data    = memory[word_address];

    /*
    * Synchronous write
    */
    always_ff @(posedge clk) begin
        if (write_enable) begin
            memory[word_address] <= write_data;
        end else begin
            memory[word_address] <= memory[word_address];
        end
    end

endmodule

rtl/memory/instruction_rom.sv
import riscv_pkg::*;

module instruction_rom #(
    parameter int XLEN        = 32,
    parameter int DEPTH_WORDS = 1024
) (
    input logic [XLEN-1:0] address,
    output logic [INSTRUCTION_WIDTH-1:0] instruction
);
    /*
    * ROM storage
    */
    logic [INSTRUCTION_WIDTH-1:0] memory[DEPTH_WORDS];
    logic [$clog2(DEPTH_WORDS)-1:0] word_address;

    assign word_address = address / INSTRUCTION_BYTES;

    /*
    * Asynchronous read
    */
    assign instruction  = memory[word_address];

    /*
    * Load program at sim time
    */
    initial begin
        $readmemh("main.hex", memory);
    end

endmodule

rtl/core/core.sv
import riscv_pkg::*;

module core #(
    parameter int XLEN = 32
) (
    input logic clk,
    input logic n_rst,

    output logic [XLEN-1:0] program_counter,
    input logic [INSTRUCTION_WIDTH-1:0] instruction,

    output logic memory_write_enable,
    output logic [XLEN-1:0] memory_address,
    output logic [XLEN-1:0] memory_write_data,
    input logic [XLEN-1:0] memory_read_data
);

    /*
    * Architectural state
    */
    logic [XLEN-1:0] program_counter_next;
    logic [XLEN-1:0] registers[REGISTER_COUNT-1:0];
    logic [XLEN-1:0] registers_next[REGISTER_COUNT-1:0];

    /*
    * Decode
    */
    logic [OPCODE_FIELD_WIDTH-1:0] instruction_class;
    logic [REGISTER_INDEX_WIDTH-1:0] destination_register_index;
    logic [REGISTER_INDEX_WIDTH-1:0] source_register_1_index;
    logic [REGISTER_INDEX_WIDTH-1:0] source_register_2_index;

    /*
    * Immediate values
    */
    logic [XLEN-1:0] immediate_i;
    logic [XLEN-1:0] immediate_s;
    logic [XLEN-1:0] immediate_j;

    /*
    * Decode logic
    */
    assign instruction_class = instruction[OPCODE_MSB:OPCODE_LSB];
    assign destination_register_index = instruction[DEST_REG_MSB:DEST_REG_LSB];
    assign source_register_1_index = instruction[SRC_REG1_MSB:SRC_REG1_LSB];
    assign source_register_2_index = instruction[SRC_REG2_MSB:SRC_REG2_LSB];

    assign immediate_i = {{(XLEN - 12) {instruction[31]}}, instruction[31:20]};
    assign immediate_s = {{(XLEN - 12) {instruction[31]}}, instruction[31:25], instruction[11:7]};
    assign immediate_j = {
        {(XLEN - 12) {instruction[31]}}, instruction[19:12], instruction[20], instruction[30:21]
    };

    /*
    * Execute
    */
    always_comb begin
        // Default behavior
        program_counter_next = program_counter + INSTRUCTION_BYTES;
        for (int i = 0; i < REGISTER_COUNT; i++) begin
            registers_next[i] = registers[i];
        end
        memory_write_enable = 1'b0;
        memory_address      = '0;
        memory_write_data   = '0;

        // Instruction specific
        case (instruction_class)
            // Integer arithmetic with immediate
            CLASS_OP_IMM: begin
                registers_next[destination_register_index] = registers[source_register_1_index] + immediate_i;
            end
            // Jump and link
            CLASS_JAL: begin
                registers_next[destination_register_index] = program_counter + INSTRUCTION_BYTES;
                program_counter_next                       = program_counter + immediate_j;
            end
            // Store to memory
            CLASS_STORE: begin
                memory_write_enable = 1'b1;
                memory_address      = registers[source_register_1_index] + immediate_s;
                memory_write_data   = registers[source_register_2_index];
            end
            default: begin
                // nop
            end
        endcase

        // Enforce register X0 = 0
        registers_next[X0] = '0;
    end

    /*
    * Commit
    */
    always_ff @(posedge clk) begin
        if (~n_rst) begin
            program_counter <= '0;
            for (int i = 0; i < REGISTER_COUNT; i++) begin
                registers[i] <= '0;
            end
        end else begin
            program_counter <= program_counter_next;
            for (int i = 0; i < REGISTER_COUNT; i++) begin
                registers_next[i] <= registers[i];
            end
        end
    end

endmodule

rtl/top.sv
import riscv_pkg::*;

/**
* top.sv
* @brief Top-level definition for a simple RISC-V SoC.
*
* @param XLEN the SoC address bit width (32 or 64).
* @param clk the provided clock for the SoC.
* @param n_rst active low reset signal for the SoC.
*/
module top #(
    parameter int XLEN = 32
) (
    input logic clk,
    input logic n_rst
);
    logic [XLEN-1:0] program_counter;
    logic [INSTRUCTION_WIDTH-1:0] instruction;

    logic memory_write_enable;
    logic [XLEN-1:0] memory_address;
    logic [XLEN-1:0] memory_write_data;
    logic [XLEN-1:0] memory_read_data;

    /*
    * CPU
    */
    core cpu (
        .clk  (clk),
        .n_rst(n_rst),

        .program_counter(program_counter),
        .instruction    (instruction_register),

        .memory_write_enable(memory_write_enable),
        .memory_address     (memory_address),
        .memory_write_data  (memory_write_data),
        .memory_read_data   (memory_read_data)
    );

    /*
    * Memory
    */
    instruction_rom rom (
        .address    (program_counter),
        .instruction(instruction_register)
    );

    data_ram ram (
        .clk         (clk),
        .write_enable(memory_write_enable),
        .address     (memory_address),
        .write_data  (memory_write_data),
        .read_data   (memory_read_data)
    );

endmodule

sim/tb_top.sv
import tb_pkg::*;

module tb_top;
    logic clk;
    logic n_rst;

    // Instantiate DUT
    top dut (
        .clk  (clk),
        .n_rst(n_rst)
    );

    // ----------------------------------------
    // Clock generation
    // ----------------------------------------
    initial begin
        clk = 0;
        forever #5 clk = ~clk;
    end

    // ----------------------------------------
    // Reset sequence
    // ----------------------------------------
    initial begin
        n_rst = 0;
        #20;
        n_rst = 1;
    end

    // ----------------------------------------
    // Waveform dumping
    // ----------------------------------------
    initial begin
        $dumpfile("wave.vcd");
        $dumpvars(0, dut);
    end

    // ----------------------------------------
    // MMIO monitor
    // ----------------------------------------
    always @(posedge clk) begin
        if (dut.cpu.memory_write_enable) begin

            // PRINT
            if (dut.cpu.memory_address == MMIO_PRINT_ADDR) begin
                $display("[TB PRINT] %0d (0x%08x)", dut.cpu.memory_write_data,
                         dut.cpu.memory_write_data);
            end

            // DONE
            if (dut.cpu.memory_address == MMIO_DONE_ADDR) begin
                $display("[TB] PROGRAM DONE");
                $finish;
            end
        end
    end

    // ----------------------------------------
    // Timeout
    // ----------------------------------------
    initial begin
        #100000;
        $display("[TB] TIMEOUT");
        $finish;
    end

endmodule

sim/wave.vcd
$date
	Mon Dec 15 23:33:14 2025
$end
$version
	Icarus Verilog
$end
$timescale
	1s
$end
$scope module tb_top $end
$scope module dut $end
$var wire 1 ! clk $end
$var wire 1 " n_rst $end
$var wire 32 # program_counter [31:0] $end
$var wire 1 $ memory_write_enable $end
$var wire 32 % memory_write_data [31:0] $end
$var wire 32 & memory_read_data [31:0] $end
$var wire 32 ' memory_address [31:0] $end
$var wire 32 ( instruction [31:0] $end
$var parameter 32 ) XLEN $end
$scope module cpu $end
$var wire 1 ! clk $end
$var wire 1 " n_rst $end
$var wire 5 * source_register_2_index [4:0] $end
$var wire 5 + source_register_1_index [4:0] $end
$var wire 32 , memory_read_data [31:0] $end
$var wire 7 - instruction_class [6:0] $end
$var wire 32 . instruction [31:0] $end
$var wire 32 / immediate_s [31:0] $end
$var wire 32 0 immediate_j [31:0] $end
$var wire 32 1 immediate_i [31:0] $end
$var wire 5 2 destination_register_index [4:0] $end
$var parameter 32 3 XLEN $end
$var reg 32 4 memory_address [31:0] $end
$var reg 32 5 memory_write_data [31:0] $end
$var reg 1 $ memory_write_enable $end
$var reg 32 6 program_counter [31:0] $end
$var reg 32 7 program_counter_next [31:0] $end
$scope begin $ivl_for_loop0 $end
$var integer 32 8 i [31:0] $end
$upscope $end
$scope begin $ivl_for_loop1 $end
$var integer 32 9 i [31:0] $end
$upscope $end
$scope begin $ivl_for_loop2 $end
$var integer 32 : i [31:0] $end
$upscope $end
$upscope $end
$scope module ram $end
$var wire 32 ; address [31:0] $end
$var wire 1 ! clk $end
$var wire 32 < read_data [31:0] $end
$var wire 32 = write_data [31:0] $end
$var wire 1 $ write_enable $end
$var wire 10 > word_address [9:0] $end
$var parameter 32 ? DEPTH_WORDS $end
$var parameter 32 @ XLEN $end
$upscope $end
$scope module rom $end
$var wire 32 A address [31:0] $end
$var wire 32 B instruction [31:0] $end
$var wire 10 C word_address [9:0] $end
$var parameter 32 D DEPTH_WORDS $end
$var parameter 32 E XLEN $end
$upscope $end
$upscope $end
$upscope $end
$enddefinitions $end
$comment Show the parameter values. $end
$dumpall
b100000 E
b10000000000 D
b100000 @
b10000000000 ?
b100000 3
b100000 )
$end
#0
$dumpvars
bx C
bx B
bx A
b0 >
b0 =
bx <
b0 ;
b0 :
b0 9
b100000 8
bx 7
bx 6
b0 5
b0 4
bx 2
bx 1
bx 0
bx /
bx .
bx -
bx ,
bx +
bx *
bx (
b0 '
bx &
b0 %
0$
bx #
0"
0!
$end
#5
b0 0
b0 /
b0 1
b0 *
b0 +
b0 2
b10011 -
b100000 8
b100 7
b10011 (
b10011 .
b10011 B
b0 C
b0 #
b0 6
b0 A
b100000 9
1!
#10
0!
#15
b100000 9
1!
#20
0!
1"
#25
b1 -
b100000 8
b1000 7
b1 (
b1 .
b1 B
b1 C
b100 #
b100 6
b100 A
b100000 :
1!
#30
0!
#35
b0 -
b100000 8
b1100 7
b0 (
b0 .
b0 B
b10 C
b1000 #
b1000 6
b1000 A
b100000 :
1!
#40
0!
#45
b1000101 -
b100000 8
b10000 7
b1000101 (
b1000101 .
b1000101 B
b11 C
b1100 #
b1100 6
b1100 A
b100000 :
1!
#50
0!
#55
b1 /
b1 2
b1101111 -
b100000 8
b10100 7
b11101111 (
b11101111 .
b11101111 B
b100 C
b10000 #
b10000 6
b10000 A
b100000 :
1!
#60
0!
#65
b0 /
b0 2
b0 -
b100000 8
b11000 7
b0 (
b0 .
b0 B
b101 C
b10100 #
b10100 6
b10100 A
b100000 :
1!
#70
0!
#75
b1 /
b1 2
b100000 8
b11100 7
b10000000 (
b10000000 .
b10000000 B
b110 C
b11000 #
b11000 6
b11000 A
b100000 :
1!
#80
0!
#85
b0 /
b0 2
b100000 8
b100000 7
b0 (
b0 .
b0 B
b111 C
b11100 #
b11100 6
b11100 A
b100000 :
1!
#90
0!
#95
b1101111 -
b100000 8
b100100 7
b1101111 (
b1101111 .
b1101111 B
b1000 C
b100000 #
b100000 6
b100000 A
b100000 :
1!
#100
0!
#105
b0 -
b100000 8
b101000 7
b0 (
b0 .
b0 B
b1001 C
b100100 #
b100100 6
b100100 A
b100000 :
1!
#110
0!
#115
b100000 8
b101100 7
b1010 C
b101000 #
b101000 6
b101000 A
b100000 :
1!
#120
0!
#125
b100000 8
b110000 7
b1011 C
b101100 #
b101100 6
b101100 A
b100000 :
1!
#130
0!
#135
b10011 -
b100000 8
b110100 7
b10011 (
b10011 .
b10011 B
b1100 C
b110000 #
b110000 6
b110000 A
b100000 :
1!
#140
0!
#145
b1 -
b100000 8
b111000 7
b1 (
b1 .
b1 B
b1101 C
b110100 #
b110100 6
b110100 A
b100000 :
1!
#150
0!
#155
b100000 8
b111100 7
b1110 C
b111000 #
b111000 6
b111000 A
b100000 :
1!
#160
0!
#165
b1 /
b1 2
b1111111 -
b100000 8
b1000000 7
b11111111 (
b11111111 .
b11111111 B
b1111 C
b111100 #
b111100 6
b111100 A
b100000 :
1!
#170
0!
#175
b0 /
b0 2
b100011 -
b100000 8
b1000000 7
b100011 (
b100011 .
b100011 B
b10000 C
b1000000 #
b1000000 6
b1000000 A
b100000 :
1!
#180
0!
#185
b100000 :
1!
#190
0!
#195
b100000 :
1!
#200
0!
#205
b100000 :
1!
#210
0!
#215
b100000 :
1!
#220
0!
#225
b100000 :
1!
#230
0!
#235
b100000 :
1!
#240
0!
#245
b100000 :
1!
#250
0!
#255
b100000 :
1!
#260
0!
#265
b100000 :
1!
#270
0!
#275
b100000 :
1!
#280
0!
#285
b100000 :
1!
#290
0!
#295
b100000 :
1!
#300
0!
#305
b100000 :
1!
#310
0!
#315
b100000 :
1!
#320
0!
#325
b100000 :
1!
#330
0!
#335
b100000 :
1!
#340
0!
#345
b100000 :
1!
#350
0!
#355
b100000 :
1!
#360
0!
#365
b100000 :
1!
#370
0!
#375
b100000 :
1!
#380
0!
#385
b100000 :
1!
#390
0!
#395
b100000 :
1!
#400
0!
#405
b100000 :
1!
#410
0!
#415
b100000 :
1!
#420
0!
#425
b100000 :
1!
#430
0!
#435
b100000 :
1!
#440
0!
#445
b100000 :
1!
#450
0!
#455
b100000 :
1!
#460
0!
#465
b100000 :
1!
#470
0!
#475
b100000 :
1!
#480
0!
#485
b100000 :
1!
#490
0!
#495
b100000 :
1!
#500
0!
#505
b100000 :
1!
#510
0!
#515
b100000 :
1!
#520
0!
#525
b100000 :
1!
#530
0!
#535
b100000 :
1!
#540
0!
#545
b100000 :
1!
#550
0!
#555
b100000 :
1!
#560
0!
#565
b100000 :
1!
#570
0!
#575
b100000 :
1!
#580
0!
#585
b100000 :
1!
#590
0!
#595
b100000 :
1!
#600
0!
#605
b100000 :
1!
#610
0!
#615
b100000 :
1!
#620
0!
#625
b100000 :
1!
#630
0!
#635
b100000 :
1!
#640
0!
#645
b100000 :
1!
#650
0!
#655
b100000 :
1!
#660
0!
#665
b100000 :
1!
#670
0!
#675
b100000 :
1!
#680
0!
#685
b100000 :
1!
#690
0!
#695
b100000 :
1!
#700
0!
#705
b100000 :
1!
#710
0!
#715
b100000 :
1!
#720
0!
#725
b100000 :
1!
#730
0!
#735
b100000 :
1!
#740
0!
#745
b100000 :
1!
#750
0!
#755
b100000 :
1!
#760
0!
#765
b100000 :
1!
#770
0!
#775
b100000 :
1!
#780
0!
#785
b100000 :
1!
#790
0!
#795
b100000 :
1!
#800
0!
#805
b100000 :
1!
#810
0!
#815
b100000 :
1!
#820
0!
#825
b100000 :
1!
#830
0!
#835
b100000 :
1!
#840
0!
#845
b100000 :
1!
#850
0!
#855
b100000 :
1!
#860
0!
#865
b100000 :
1!
#870
0!
#875
b100000 :
1!
#880
0!
#885
b100000 :
1!
#890
0!
#895
b100000 :
1!
#900
0!
#905
b100000 :
1!
#910
0!
#915
b100000 :
1!
#920
0!
#925
b100000 :
1!
#930
0!
#935
b100000 :
1!
#940
0!
#945
b100000 :
1!
#950
0!
#955
b100000 :
1!
#960
0!
#965
b100000 :
1!
#970
0!
#975
b100000 :
1!
#980
0!
#985
b100000 :
1!
#990
0!
#995
b100000 :
1!
#1000
0!
#1005
b100000 :
1!
#1010
0!
#1015
b100000 :
1!
#1020
0!
#1025
b100000 :
1!
#1030
0!
#1035
b100000 :
1!
#1040
0!
#1045
b100000 :
1!
#1050
0!
#1055
b100000 :
1!
#1060
0!
#1065
b100000 :
1!
#1070
0!
#1075
b100000 :
1!
#1080
0!
#1085
b100000 :
1!
#1090
0!
#1095
b100000 :
1!
#1100
0!
#1105
b100000 :
1!
#1110
0!
#1115
b100000 :
1!
#1120
0!
#1125
b100000 :
1!
#1130
0!
#1135
b100000 :
1!
#1140
0!
#1145
b100000 :
1!
#1150
0!
#1155
b100000 :
1!
#1160
0!
#1165
b100000 :
1!
#1170
0!
#1175
b100000 :
1!
#1180
0!
#1185
b100000 :
1!
#1190
0!
#1195
b100000 :
1!
#1200
0!
#1205
b100000 :
1!
#1210
0!
#1215
b100000 :
1!
#1220
0!
#1225
b100000 :
1!
#1230
0!
#1235
b100000 :
1!
#1240
0!
#1245
b100000 :
1!
#1250
0!
#1255
b100000 :
1!
#1260
0!
#1265
b100000 :
1!
#1270
0!
#1275
b100000 :
1!
#1280
0!
#1285
b100000 :
1!
#1290
0!
#1295
b100000 :
1!
#1300
0!
#1305
b100000 :
1!
#1310
0!
#1315
b100000 :
1!
#1320
0!
#1325
b100000 :
1!
#1330
0!
#1335
b100000 :
1!
#1340
0!
#1345
b100000 :
1!
#1350
0!
#1355
b100000 :
1!
#1360
0!
#1365
b100000 :
1!
#1370
0!
#1375
b100000 :
1!
#1380
0!
#1385
b100000 :
1!
#1390
0!
#1395
b100000 :
1!
#1400
0!
#1405
b100000 :
1!
#1410
0!
#1415
b100000 :
1!
#1420
0!
#1425
b100000 :
1!
#1430
0!
#1435
b100000 :
1!
#1440
0!
#1445
b100000 :
1!
#1450
0!
#1455
b100000 :
1!
#1460
0!
#1465
b100000 :
1!
#1470
0!
#1475
b100000 :
1!
#1480
0!
#1485
b100000 :
1!
#1490
0!
#1495
b100000 :
1!
#1500
0!
#1505
b100000 :
1!
#1510
0!
#1515
b100000 :
1!
#1520
0!
#1525
b100000 :
1!
#1530
0!
#1535
b100000 :
1!
#1540
0!
#1545
b100000 :
1!
#1550
0!
#1555
b100000 :
1!
#1560
0!
#1565
b100000 :
1!
#1570
0!
#1575
b100000 :
1!
#1580
0!
#1585
b100000 :
1!
#1590
0!
#1595
b100000 :
1!
#1600
0!
#1605
b100000 :
1!
#1610
0!
#1615
b100000 :
1!
#1620
0!
#1625
b100000 :
1!
#1630
0!
#1635
b100000 :
1!
#1640
0!
#1645
b100000 :
1!
#1650
0!
#1655
b100000 :
1!
#1660
0!
#1665
b100000 :
1!
#1670
0!
#1675
b100000 :
1!
#1680
0!
#1685
b100000 :
1!
#1690
0!
#1695
b100000 :
1!
#1700
0!
#1705
b100000 :
1!
#1710
0!
#1715
b100000 :
1!
#1720
0!
#1725
b100000 :
1!
#1730
0!
#1735
b100000 :
1!
#1740
0!
#1745
b100000 :
1!
#1750
0!
#1755
b100000 :
1!
#1760
0!
#1765
b100000 :
1!
#1770
0!
#1775
b100000 :
1!
#1780
0!
#1785
b100000 :
1!
#1790
0!
#1795
b100000 :
1!
#1800
0!
#1805
b100000 :
1!
#1810
0!
#1815
b100000 :
1!
#1820
0!
#1825
b100000 :
1!
#1830
0!
#1835
b100000 :
1!
#1840
0!
#1845
b100000 :
1!
#1850
0!
#1855
b100000 :
1!
#1860
0!
#1865
b100000 :
1!
#1870
0!
#1875
b100000 :
1!
#1880
0!
#1885
b100000 :
1!
#1890
0!
#1895
b100000 :
1!
#1900
0!
#1905
b100000 :
1!
#1910
0!
#1915
b100000 :
1!
#1920
0!
#1925
b100000 :
1!
#1930
0!
#1935
b100000 :
1!
#1940
0!
#1945
b100000 :
1!
#1950
0!
#1955
b100000 :
1!
#1960
0!
#1965
b100000 :
1!
#1970
0!
#1975
b100000 :
1!
#1980
0!
#1985
b100000 :
1!
#1990
0!
#1995
b100000 :
1!
#2000
0!
#2005
b100000 :
1!
#2010
0!
#2015
b100000 :
1!
#2020
0!
#2025
b100000 :
1!
#2030
0!
#2035
b100000 :
1!
#2040
0!
#2045
b100000 :
1!
#2050
0!
#2055
b100000 :
1!
#2060
0!
#2065
b100000 :
1!
#2070
0!
#2075
b100000 :
1!
#2080
0!
#2085
b100000 :
1!
#2090
0!
#2095
b100000 :
1!
#2100
0!
#2105
b100000 :
1!
#2110
0!
#2115
b100000 :
1!
#2120
0!
#2125
b100000 :
1!
#2130
0!
#2135
b100000 :
1!
#2140
0!
#2145
b100000 :
1!
#2150
0!
#2155
b100000 :
1!
#2160
0!
#2165
b100000 :
1!
#2170
0!
#2175
b100000 :
1!
#2180
0!
#2185
b100000 :
1!
#2190
0!
#2195
b100000 :
1!
#2200
0!
#2205
b100000 :
1!
#2210
0!
#2215
b100000 :
1!
#2220
0!
#2225
b100000 :
1!
#2230
0!
#2235
b100000 :
1!
#2240
0!
#2245
b100000 :
1!
#2250
0!
#2255
b100000 :
1!
#2260
0!
#2265
b100000 :
1!
#2270
0!
#2275
b100000 :
1!
#2280
0!
#2285
b100000 :
1!
#2290
0!
#2295
b100000 :
1!
#2300
0!
#2305
b100000 :
1!
#2310
0!
#2315
b100000 :
1!
#2320
0!
#2325
b100000 :
1!
#2330
0!
#2335
b100000 :
1!
#2340
0!
#2345
b100000 :
1!
#2350
0!
#2355
b100000 :
1!
#2360
0!
#2365
b100000 :
1!
#2370
0!
#2375
b100000 :
1!
#2380
0!
#2385
b100000 :
1!
#2390
0!
#2395
b100000 :
1!
#2400
0!
#2405
b100000 :
1!
#2410
0!
#2415
b100000 :
1!
#2420
0!
#2425
b100000 :
1!
#2430
0!
#2435
b100000 :
1!
#2440
0!
#2445
b100000 :
1!
#2450
0!
#2455
b100000 :
1!
#2460
0!
#2465
b100000 :
1!
#2470
0!
#2475
b100000 :
1!
#2480
0!
#2485
b100000 :
1!
#2490
0!
#2495
b100000 :
1!
#2500
0!
#2505
b100000 :
1!
#2510
0!
#2515
b100000 :
1!
#2520
0!
#2525
b100000 :
1!
#2530
0!
#2535
b100000 :
1!
#2540
0!
#2545
b100000 :
1!
#2550
0!
#2555
b100000 :
1!
#2560
0!
#2565
b100000 :
1!
#2570
0!
#2575
b100000 :
1!
#2580
0!
#2585
b100000 :
1!
#2590
0!
#2595
b100000 :
1!
#2600
0!
#2605
b100000 :
1!
#2610
0!
#2615
b100000 :
1!
#2620
0!
#2625
b100000 :
1!
#2630
0!
#2635
b100000 :
1!
#2640
0!
#2645
b100000 :
1!
#2650
0!
#2655
b100000 :
1!
#2660
0!
#2665
b100000 :
1!
#2670
0!
#2675
b100000 :
1!
#2680
0!
#2685
b100000 :
1!
#2690
0!
#2695
b100000 :
1!
#2700
0!
#2705
b100000 :
1!
#2710
0!
#2715
b100000 :
1!
#2720
0!
#2725
b100000 :
1!
#2730
0!
#2735
b100000 :
1!
#2740
0!
#2745
b100000 :
1!
#2750
0!
#2755
b100000 :
1!
#2760
0!
#2765
b100000 :
1!
#2770
0!
#2775
b100000 :
1!
#2780
0!
#2785
b100000 :
1!
#2790
0!
#2795
b100000 :
1!
#2800
0!
#2805
b100000 :
1!
#2810
0!
#2815
b100000 :
1!
#2820
0!
#2825
b100000 :
1!
#2830
0!
#2835
b100000 :
1!
#2840
0!
#2845
b100000 :
1!
#2850
0!
#2855
b100000 :
1!
#2860
0!
#2865
b100000 :
1!
#2870
0!
#2875
b100000 :
1!
#2880
0!
#2885
b100000 :
1!
#2890
0!
#2895
b100000 :
1!
#2900
0!
#2905
b100000 :
1!
#2910
0!
#2915
b100000 :
1!
#2920
0!
#2925
b100000 :
1!
#2930
0!
#2935
b100000 :
1!
#2940
0!
#2945
b100000 :
1!
#2950
0!
#2955
b100000 :
1!
#2960
0!
#2965
b100000 :
1!
#2970
0!
#2975
b100000 :
1!
#2980
0!
#2985
b100000 :
1!
#2990
0!
#2995
b100000 :
1!
#3000
0!
#3005
b100000 :
1!
#3010
0!
#3015
b100000 :
1!
#3020
0!
#3025
b100000 :
1!
#3030
0!
#3035
b100000 :
1!
#3040
0!
#3045
b100000 :
1!
#3050
0!
#3055
b100000 :
1!
#3060
0!
#3065
b100000 :
1!
#3070
0!
#3075
b100000 :
1!
#3080
0!
#3085
b100000 :
1!
#3090
0!
#3095
b100000 :
1!
#3100
0!
#3105
b100000 :
1!
#3110
0!
#3115
b100000 :
1!
#3120
0!
#3125
b100000 :
1!
#3130
0!
#3135
b100000 :
1!
#3140
0!
#3145
b100000 :
1!
#3150
0!
#3155
b100000 :
1!
#3160
0!
#3165
b100000 :
1!
#3170
0!
#3175
b100000 :
1!
#3180
0!
#3185
b100000 :
1!
#3190
0!
#3195
b100000 :
1!
#3200
0!
#3205
b100000 :
1!
#3210
0!
#3215
b100000 :
1!
#3220
0!
#3225
b100000 :
1!
#3230
0!
#3235
b100000 :
1!
#3240
0!
#3245
b100000 :
1!
#3250
0!
#3255
b100000 :
1!
#3260
0!
#3265
b100000 :
1!
#3270
0!
#3275
b100000 :
1!
#3280
0!
#3285
b100000 :
1!
#3290
0!
#3295
b100000 :
1!
#3300
0!
#3305
b100000 :
1!
#3310
0!
#3315
b100000 :
1!
#3320
0!
#3325
b100000 :
1!
#3330
0!
#3335
b100000 :
1!
#3340
0!
#3345
b100000 :
1!
#3350
0!
#3355
b100000 :
1!
#3360
0!
#3365
b100000 :
1!
#3370
0!
#3375
b100000 :
1!
#3380
0!
#3385
b100000 :
1!
#3390
0!
#3395
b100000 :
1!
#3400
0!
#3405
b100000 :
1!
#3410
0!
#3415
b100000 :
1!
#3420
0!
#3425
b100000 :
1!
#3430
0!
#3435
b100000 :
1!
#3440
0!
#3445
b100000 :
1!
#3450
0!
#3455
b100000 :
1!
#3460
0!
#3465
b100000 :
1!
#3470
0!
#3475
b100000 :
1!
#3480
0!
#3485
b100000 :
1!
#3490
0!
#3495
b100000 :
1!
#3500
0!
#3505
b100000 :
1!
#3510
0!
#3515
b100000 :
1!
#3520
0!
#3525
b100000 :
1!
#3530
0!
#3535
b100000 :
1!
#3540
0!
#3545
b100000 :
1!
#3550
0!
#3555
b100000 :
1!
#3560
0!
#3565
b100000 :
1!
#3570
0!
#3575
b100000 :
1!
#3580
0!
#3585
b100000 :
1!
#3590
0!
#3595
b100000 :
1!
#3600
0!
#3605
b100000 :
1!
#3610
0!
#3615
b100000 :
1!
#3620
0!
#3625
b100000 :
1!
#3630
0!
#3635
b100000 :
1!
#3640
0!
#3645
b100000 :
1!
#3650
0!
#3655
b100000 :
1!
#3660
0!
#3665
b100000 :
1!
#3670
0!
#3675
b100000 :
1!
#3680
0!
#3685
b100000 :
1!
#3690
0!
#3695
b100000 :
1!
#3700
0!
#3705
b100000 :
1!
#3710
0!
#3715
b100000 :
1!
#3720
0!
#3725
b100000 :
1!
#3730
0!
#3735
b100000 :
1!
#3740
0!
#3745
b100000 :
1!
#3750
0!
#3755
b100000 :
1!
#3760
0!
#3765
b100000 :
1!
#3770
0!
#3775
b100000 :
1!
#3780
0!
#3785
b100000 :
1!
#3790
0!
#3795
b100000 :
1!
#3800
0!
#3805
b100000 :
1!
#3810
0!
#3815
b100000 :
1!
#3820
0!
#3825
b100000 :
1!
#3830
0!
#3835
b100000 :
1!
#3840
0!
#3845
b100000 :
1!
#3850
0!
#3855
b100000 :
1!
#3860
0!
#3865
b100000 :
1!
#3870
0!
#3875
b100000 :
1!
#3880
0!
#3885
b100000 :
1!
#3890
0!
#3895
b100000 :
1!
#3900
0!
#3905
b100000 :
1!
#3910
0!
#3915
b100000 :
1!
#3920
0!
#3925
b100000 :
1!
#3930
0!
#3935
b100000 :
1!
#3940
0!
#3945
b100000 :
1!
#3950
0!
#3955
b100000 :
1!
#3960
0!
#3965
b100000 :
1!
#3970
0!
#3975
b100000 :
1!
#3980
0!
#3985
b100000 :
1!
#3990
0!
#3995
b100000 :
1!
#4000
0!
#4005
b100000 :
1!
#4010
0!
#4015
b100000 :
1!
#4020
0!
#4025
b100000 :
1!
#4030
0!
#4035
b100000 :
1!
#4040
0!
#4045
b100000 :
1!
#4050
0!
#4055
b100000 :
1!
#4060
0!
#4065
b100000 :
1!
#4070
0!
#4075
b100000 :
1!
#4080
0!
#4085
b100000 :
1!
#4090
0!
#4095
b100000 :
1!
#4100
0!
#4105
b100000 :
1!
#4110
0!
#4115
b100000 :
1!
#4120
0!
#4125
b100000 :
1!
#4130
0!
#4135
b100000 :
1!
#4140
0!
#4145
b100000 :
1!
#4150
0!
#4155
b100000 :
1!
#4160
0!
#4165
b100000 :
1!
#4170
0!
#4175
b100000 :
1!
#4180
0!
#4185
b100000 :
1!
#4190
0!
#4195
b100000 :
1!
#4200
0!
#4205
b100000 :
1!
#4210
0!
#4215
b100000 :
1!
#4220
0!
#4225
b100000 :
1!
#4230
0!
#4235
b100000 :
1!
#4240
0!
#4245
b100000 :
1!
#4250
0!
#4255
b100000 :
1!
#4260
0!
#4265
b100000 :
1!
#4270
0!
#4275
b100000 :
1!
#4280
0!
#4285
b100000 :
1!
#4290
0!
#4295
b100000 :
1!
#4300
0!
#4305
b100000 :
1!
#4310
0!
#4315
b100000 :
1!
#4320
0!
#4325
b100000 :
1!
#4330
0!
#4335
b100000 :
1!
#4340
0!
#4345
b100000 :
1!
#4350
0!
#4355
b100000 :
1!
#4360
0!
#4365
b100000 :
1!
#4370
0!
#4375
b100000 :
1!
#4380
0!
#4385
b100000 :
1!
#4390
0!
#4395
b100000 :
1!
#4400
0!
#4405
b100000 :
1!
#4410
0!
#4415
b100000 :
1!
#4420
0!
#4425
b100000 :
1!
#4430
0!
#4435
b100000 :
1!
#4440
0!
#4445
b100000 :
1!
#4450
0!
#4455
b100000 :
1!
#4460
0!
#4465
b100000 :
1!
#4470
0!
#4475
b100000 :
1!
#4480
0!
#4485
b100000 :
1!
#4490
0!
#4495
b100000 :
1!
#4500
0!
#4505
b100000 :
1!
#4510
0!
#4515
b100000 :
1!
#4520
0!
#4525
b100000 :
1!
#4530
0!
#4535
b100000 :
1!
#4540
0!
#4545
b100000 :
1!
#4550
0!
#4555
b100000 :
1!
#4560
0!
#4565
b100000 :
1!
#4570
0!
#4575
b100000 :
1!
#4580
0!
#4585
b100000 :
1!
#4590
0!
#4595
b100000 :
1!
#4600
0!
#4605
b100000 :
1!
#4610
0!
#4615
b100000 :
1!
#4620
0!
#4625
b100000 :
1!
#4630
0!
#4635
b100000 :
1!
#4640
0!
#4645
b100000 :
1!
#4650
0!
#4655
b100000 :
1!
#4660
0!
#4665
b100000 :
1!
#4670
0!
#4675
b100000 :
1!
#4680
0!
#4685
b100000 :
1!
#4690
0!
#4695
b100000 :
1!
#4700
0!
#4705
b100000 :
1!
#4710
0!
#4715
b100000 :
1!
#4720
0!
#4725
b100000 :
1!
#4730
0!
#4735
b100000 :
1!
#4740
0!
#4745
b100000 :
1!
#4750
0!
#4755
b100000 :
1!
#4760
0!
#4765
b100000 :
1!
#4770
0!
#4775
b100000 :
1!
#4780
0!
#4785
b100000 :
1!
#4790
0!
#4795
b100000 :
1!
#4800
0!
#4805
b100000 :
1!
#4810
0!
#4815
b100000 :
1!
#4820
0!
#4825
b100000 :
1!
#4830
0!
