rtl/memory/data_ram.sv
import riscv_pkg::*;

module data_ram #(
    parameter int XLEN        = 32,
    parameter int DEPTH_WORDS = 1024
) (
    input logic clk,
    input logic write_enable,
    input logic [XLEN-1:0] address,
    input logic [XLEN-1:0] write_data,
    output logic [XLEN-1:0] read_data
);

    logic [XLEN-1:0] memory[DEPTH_WORDS];
    logic [$clog2(DEPTH_WORDS)-1:0] word_address;

    assign word_address = address / INSTRUCTION_BYTES;

    /*
    * Asynchronous read
    */
    assign read_data    = memory[word_address];

    /*
    * Synchronous write
    */
    always_ff @(posedge clk) begin
        if (write_enable) begin
            memory[word_address] <= write_data;
        end else begin
            memory[word_address] <= memory[word_address];
        end
    end

endmodule

rtl/memory/instruction_rom.sv
import riscv_pkg::*;

module instruction_rom #(
    parameter int XLEN        = 32,
    parameter int DEPTH_WORDS = 1024
) (
    input logic [XLEN-1:0] address,
    output logic [INSTRUCTION_WIDTH-1:0] instruction
);
    /*
    * ROM storage
    * main.hex produced by objcopy is byte-addressed, so store bytes and
    * reassemble words on the fly.
    */
    localparam int DEPTH_BYTES = DEPTH_WORDS * INSTRUCTION_BYTES;

    logic [BYTE_WIDTH-1:0] memory[DEPTH_BYTES];
    logic [$clog2(DEPTH_WORDS)-1:0] word_address;

    assign word_address = address / INSTRUCTION_BYTES;

    /*
    * Asynchronous read (little-endian)
    */
    assign instruction = {
        memory[(word_address * INSTRUCTION_BYTES) + 3],
        memory[(word_address * INSTRUCTION_BYTES) + 2],
        memory[(word_address * INSTRUCTION_BYTES) + 1],
        memory[(word_address * INSTRUCTION_BYTES) + 0]
    };

    /*
    * Load program at sim time
    */
    initial begin
        $readmemh("main.hex", memory);
    end

endmodule

rtl/core/core.sv
import riscv_pkg::*;

module core #(
    parameter int XLEN = 32
) (
    input logic clk,
    input logic n_rst,

    output logic [XLEN-1:0] program_counter,
    input logic [INSTRUCTION_WIDTH-1:0] instruction,

    output logic memory_write_enable,
    output logic [XLEN-1:0] memory_address,
    output logic [XLEN-1:0] memory_write_data,
    input logic [XLEN-1:0] memory_read_data
);

    /*
    * Architectural state
    */
    logic [XLEN-1:0] program_counter_next;
    logic [XLEN-1:0] registers[REGISTER_COUNT-1:0];
    logic [XLEN-1:0] registers_next[REGISTER_COUNT-1:0];

    /*
    * Decode
    */
    logic [OPCODE_FIELD_WIDTH-1:0] instruction_class;
    logic [REGISTER_INDEX_WIDTH-1:0] destination_register_index;
    logic [REGISTER_INDEX_WIDTH-1:0] source_register_1_index;
    logic [REGISTER_INDEX_WIDTH-1:0] source_register_2_index;

    /*
    * Immediate values
    */
    logic [XLEN-1:0] immediate_i;
    logic [XLEN-1:0] immediate_s;
    logic [XLEN-1:0] immediate_j;

    /*
    * Decode logic
    */
    assign instruction_class = instruction[OPCODE_MSB:OPCODE_LSB];
    assign destination_register_index = instruction[DEST_REG_MSB:DEST_REG_LSB];
    assign source_register_1_index = instruction[SRC_REG1_MSB:SRC_REG1_LSB];
    assign source_register_2_index = instruction[SRC_REG2_MSB:SRC_REG2_LSB];

    assign immediate_i = {{(XLEN - 12) {instruction[31]}}, instruction[31:20]};
    assign immediate_s = {{(XLEN - 12) {instruction[31]}}, instruction[31:25], instruction[11:7]};
    assign immediate_j = {
        {(XLEN - 12) {instruction[31]}}, instruction[19:12], instruction[20], instruction[30:21], 1'b0
    };

    /*
    * Execute
    */
    always_comb begin
        // Default behavior
        program_counter_next = program_counter + INSTRUCTION_BYTES;
        for (int i = 0; i < REGISTER_COUNT; i++) begin
            registers_next[i] = registers[i];
        end
        memory_write_enable = 1'b0;
        memory_address      = '0;
        memory_write_data   = '0;

        // Instruction specific
        unique case (instruction_class)
            // Integer arithmetic with immediate
            CLASS_OP_IMM: begin
                registers_next[destination_register_index] = registers[source_register_1_index] + immediate_i;
            end
            // Jump and link
            CLASS_JAL: begin
                registers_next[destination_register_index] = program_counter + INSTRUCTION_BYTES;
                program_counter_next                       = program_counter + immediate_j;
            end
            // Store to memory
            CLASS_STORE: begin
                memory_write_enable = 1'b1;
                memory_address      = registers[source_register_1_index] + immediate_s;
                memory_write_data   = registers[source_register_2_index];
            end
            default: begin
                // nop
            end
        endcase

        // Enforce register X0 = 0
        registers_next[X0] = '0;
    end

    /*
    * Commit
    */
    always_ff @(posedge clk) begin
        if (~n_rst) begin
            program_counter <= '0;
            for (int i = 0; i < REGISTER_COUNT; i++) begin
                registers[i] <= '0;
            end
        end else begin
            program_counter <= program_counter_next;
            for (int i = 0; i < REGISTER_COUNT; i++) begin
                registers[i] <= registers_next[i];
            end
        end
    end

endmodule

rtl/top.sv
import riscv_pkg::*;

/**
* top.sv
* @brief Top-level definition for a simple RISC-V SoC.
*
* @param XLEN the SoC address bit width (32 or 64).
* @param clk the provided clock for the SoC.
* @param n_rst active low reset signal for the SoC.
*/
module top #(
    parameter int XLEN = 32
) (
    input logic clk,
    input logic n_rst
);
    logic [XLEN-1:0] program_counter;
    logic [INSTRUCTION_WIDTH-1:0] instruction;

    logic memory_write_enable;
    logic [XLEN-1:0] memory_address;
    logic [XLEN-1:0] memory_write_data;
    logic [XLEN-1:0] memory_read_data;

    /*
    * CPU
    */
    core cpu (
        .clk  (clk),
        .n_rst(n_rst),

        .program_counter(program_counter),
        .instruction    (instruction_register),

        .memory_write_enable(memory_write_enable),
        .memory_address     (memory_address),
        .memory_write_data  (memory_write_data),
        .memory_read_data   (memory_read_data)
    );

    /*
    * Memory
    */
    instruction_rom rom (
        .address    (program_counter),
        .instruction(instruction_register)
    );

    data_ram ram (
        .clk         (clk),
        .write_enable(memory_write_enable),
        .address     (memory_address),
        .write_data  (memory_write_data),
        .read_data   (memory_read_data)
    );

endmodule

sim/tb_top.sv
module tb_top;

    logic clk;
    logic n_rst;

    // Instantiate DUT
    top dut (
        .clk  (clk),
        .n_rst(n_rst)
    );

    //
    // Clock generation
    //
    initial begin
        clk = 0;
        forever #5 clk = ~clk;  // 100 MHz equivalent
    end

    //
    // Reset sequence
    //
    initial begin
        n_rst = 0;
        #20;
        n_rst = 1;
    end

    //
    // Simulation control
    //
    initial begin
        // Dump waves
        $dumpfile("wave.vcd");
        $dumpvars(0, dut);

        // Run long enough to execute program
        #1000;

        $finish;
    end

endmodule

sim/wave.vcd
$date
	Tue Dec 16 00:04:47 2025
$end
$version
	Icarus Verilog
$end
$timescale
	1s
$end
$scope module tb_top $end
$scope module dut $end
$var wire 1 ! clk $end
$var wire 1 " n_rst $end
$var wire 32 # program_counter [31:0] $end
$var wire 1 $ memory_write_enable $end
$var wire 32 % memory_write_data [31:0] $end
$var wire 32 & memory_read_data [31:0] $end
$var wire 32 ' memory_address [31:0] $end
$var wire 32 ( instruction [31:0] $end
$var parameter 32 ) XLEN $end
$scope module cpu $end
$var wire 1 ! clk $end
$var wire 1 " n_rst $end
$var wire 5 * source_register_2_index [4:0] $end
$var wire 5 + source_register_1_index [4:0] $end
$var wire 32 , memory_read_data [31:0] $end
$var wire 7 - instruction_class [6:0] $end
$var wire 32 . instruction [31:0] $end
$var wire 32 / immediate_s [31:0] $end
$var wire 32 0 immediate_j [31:0] $end
$var wire 32 1 immediate_i [31:0] $end
$var wire 5 2 destination_register_index [4:0] $end
$var parameter 32 3 XLEN $end
$var reg 32 4 memory_address [31:0] $end
$var reg 32 5 memory_write_data [31:0] $end
$var reg 1 $ memory_write_enable $end
$var reg 32 6 program_counter [31:0] $end
$var reg 32 7 program_counter_next [31:0] $end
$scope begin $ivl_for_loop0 $end
$var integer 32 8 i [31:0] $end
$upscope $end
$scope begin $ivl_for_loop1 $end
$var integer 32 9 i [31:0] $end
$upscope $end
$scope begin $ivl_for_loop2 $end
$var integer 32 : i [31:0] $end
$upscope $end
$upscope $end
$scope module ram $end
$var wire 32 ; address [31:0] $end
$var wire 1 ! clk $end
$var wire 32 < read_data [31:0] $end
$var wire 32 = write_data [31:0] $end
$var wire 1 $ write_enable $end
$var wire 10 > word_address [9:0] $end
$var parameter 32 ? DEPTH_WORDS $end
$var parameter 32 @ XLEN $end
$upscope $end
$scope module rom $end
$var wire 32 A address [31:0] $end
$var wire 10 B word_address [9:0] $end
$var wire 32 C instruction [31:0] $end
$var parameter 32 D DEPTH_BYTES $end
$var parameter 32 E DEPTH_WORDS $end
$var parameter 32 F XLEN $end
$upscope $end
$upscope $end
$upscope $end
$enddefinitions $end
$comment Show the parameter values. $end
$dumpall
b100000 F
b10000000000 E
b1000000000000 D
b100000 @
b10000000000 ?
b100000 3
b100000 )
$end
#0
$dumpvars
bx C
bx B
bx A
b0 >
b0 =
bx <
b0 ;
b0 :
b0 9
b100000 8
bx 7
bx 6
b0 5
b0 4
bx 2
bx 1
bx0 0
bx /
bx .
bx -
bx ,
bx +
bx *
bx (
b0 '
bx &
b0 %
0$
bx #
0"
0!
$end
#5
b10001010000 0
b10001010000 1
b10000 *
b0 +
b10001000010 /
b10 2
b10011 -
b100000 8
b100 7
b1000101000000000000000100010011 (
b1000101000000000000000100010011 .
b1000101000000000000000100010011 C
b0 B
b0 #
b0 6
b0 A
b100000 9
1!
#10
0!
#15
b100000 9
1!
#20
0!
1"
#25
b1000 0
b1000 1
b1000 *
b1 /
b1 2
b1101111 -
b100000 8
b1100 7
b100000000000000011101111 (
b100000000000000011101111 .
b100000000000000011101111 C
b1 B
b100 #
b100 6
b100 A
b100000 :
1!
#30
0!
#35
b11111111111100010000011111110000 0
b11111111111111111111111111110000 1
b10000 *
b10 +
b11111111111111111111111111100010 /
b10 2
b10011 -
b100000 8
b10000 7
b11111111000000010000000100010011 (
b11111111000000010000000100010011 .
b11111111000000010000000100010011 C
b11 B
b1100 #
b1100 6
b1100 A
b100000 :
1!
#40
0!
#45
b100010011 >
b10010000000001000 0
b10001001100 '
b10001001100 4
b10001001100 ;
1$
b1000 1
b1000 *
b1100 /
b1100 2
b100011 -
b100000 8
b10100 7
b100000010010011000100011 (
b100000010010011000100011 .
b100000010010011000100011 C
b100 B
b10000 #
b10000 6
b10000 A
b100000 :
1!
#50
0!
#55
b0 >
b10000000000010000 0
b10000 1
b10000 *
b1000 /
b1000 2
b10011 -
b0 '
b0 4
b0 ;
0$
b100000 8
b11000 7
b1000000010000010000010011 (
b1000000010000010000010011 .
b1000000010000010000010011 C
b101 B
bx &
bx ,
bx <
b10100 #
b10100 6
b10100 A
b100000 :
1!
#60
0!
#65
b100000100 0
b100000100 1
b100 *
b0 +
b100001111 /
b1111 2
b100000 8
b11100 7
b10000010000000000011110010011 (
b10000010000000000011110010011 .
b10000010000000000011110010011 C
b110 B
b11000 #
b11000 6
b11000 A
b100000 :
1!
#70
0!
#75
b101010 0
b101010 1
b1010 *
b101110 /
b1110 2
b100000 8
b100000 7
b10101000000000011100010011 (
b10101000000000011100010011 .
b10101000000000011100010011 C
b111 B
b11100 #
b11100 6
b11100 A
b100000 :
1!
#80
0!
#85
b1000001 >
b1111010000000001110 0
b101010 %
b101010 5
b101010 =
b100000100 '
b100000100 4
b100000100 ;
1$
b1110 1
b1110 *
b0 /
b1111 +
b0 2
b100011 -
b100000 8
b100100 7
b111001111010000000100011 (
b111001111010000000100011 .
b111001111010000000100011 C
b1000 B
b100000 #
b100000 6
b100000 A
b100000 :
1!
#90
0!
#95
b0 >
b100000100 0
b100000100 1
b100 *
b0 +
b100001111 /
b1111 2
b10011 -
b0 %
b0 5
b0 =
b0 '
b0 4
b0 ;
0$
b100000 8
b101000 7
b10000010000000000011110010011 (
b10000010000000000011110010011 .
b10000010000000000011110010011 C
b1001 B
bx &
bx ,
bx <
b100100 #
b100100 6
b100100 A
b100000 :
1!
#100
0!
#105
b110100111000 0
b10100111001 1
b11001 *
b10100101110 /
b1110 2
b100000 8
b101100 7
b1010011100100000000011100010011 (
b1010011100100000000011100010011 .
b1010011100100000000011100010011 C
b1010 B
b101000 #
b101000 6
b101000 A
b100000 :
1!
#110
0!
#115
b101010 &
b101010 ,
b101010 <
b1000001 >
b1111010000000001110 0
b10100111001 %
b10100111001 5
b10100111001 =
b100000100 '
b100000100 4
b100000100 ;
1$
b1110 1
b1110 *
b0 /
b1111 +
b0 2
b100011 -
b100000 8
b110000 7
b111001111010000000100011 (
b111001111010000000100011 .
b111001111010000000100011 C
b1011 B
b101100 #
b101100 6
b101100 A
b100000 :
1!
#120
0!
#125
b0 >
b100000100 0
b100000100 1
b100 *
b0 +
b100001111 /
b1111 2
b10011 -
b0 %
b0 5
b0 =
b0 '
b0 4
b0 ;
0$
b100000 8
b110100 7
b10000010000000000011110010011 (
b10000010000000000011110010011 .
b10000010000000000011110010011 C
b1100 B
bx &
bx ,
bx <
b110000 #
b110000 6
b110000 A
b100000 :
1!
#130
0!
#135
b11111111111111011100010111101010 0
b11111111111111111111110111101010 1
b1010 *
b11011 +
b11111111111111111111110111101110 /
b1110 2
b110111 -
b100000 8
b111000 7
b11011110101011011100011100110111 (
b11011110101011011100011100110111 .
b11011110101011011100011100110111 C
b1101 B
b110100 #
b110100 6
b110100 A
b100000 :
1!
#140
0!
#145
b11111111111101110000111011101110 0
b11111111111111111111111011101110 /
b11111111111111111111111011101111 1
b1111 *
b1110 +
b10011 -
b100000 8
b111100 7
b11101110111101110000011100010011 (
b11101110111101110000011100010011 .
b11101110111101110000011100010011 C
b1110 B
b111000 #
b111000 6
b111000 A
b100000 :
1!
#150
0!
#155
b10100111001 &
b10100111001 ,
b10100111001 <
b1000001 >
b1111010000000001110 0
b10000101000 %
b10000101000 5
b10000101000 =
b100000100 '
b100000100 4
b100000100 ;
1$
b1110 1
b1110 *
b0 /
b1111 +
b0 2
b100011 -
b100000 8
b1000000 7
b111001111010000000100011 (
b111001111010000000100011 .
b111001111010000000100011 C
b1111 B
b111100 #
b111100 6
b111100 A
b100000 :
1!
#160
0!
#165
b0 >
b100000000 0
b100000000 1
b0 *
b0 +
b100001111 /
b1111 2
b10011 -
b0 %
b0 5
b0 =
b0 '
b0 4
b0 ;
0$
b100000 8
b1000100 7
b10000000000000000011110010011 (
b10000000000000000011110010011 .
b10000000000000000011110010011 C
b10000 B
bx &
bx ,
bx <
b1000000 #
b1000000 6
b1000000 A
b100000 :
1!
#170
0!
#175
b100000000000 0
b1 1
b1 *
b1110 /
b1110 2
b100000 8
b1001000 7
b100000000011100010011 (
b100000000011100010011 .
b100000000011100010011 C
b10001 B
b1000100 #
b1000100 6
b1000100 A
b100000 :
1!
#180
0!
#185
b1000000 >
b1111010000000001110 0
b1 %
b1 5
b1 =
b100000000 '
b100000000 4
b100000000 ;
1$
b1110 1
b1110 *
b0 /
b1111 +
b0 2
b100011 -
b100000 8
b1001100 7
b111001111010000000100011 (
b111001111010000000100011 .
b111001111010000000100011 C
b10010 B
b1001000 #
b1001000 6
b1001000 A
b100000 :
1!
#190
0!
#195
b0 >
b0 0
b0 1
b0 *
b0 +
b1101111 -
b0 %
b0 5
b0 =
b0 '
b0 4
b0 ;
0$
b100000 8
b1001100 7
b1101111 (
b1101111 .
b1101111 C
b10011 B
bx &
bx ,
bx <
b1001100 #
b1001100 6
b1001100 A
b100000 :
1!
