rtl/memory/data_ram.sv
import riscv_pkg::*;

module data_ram #(
    parameter int XLEN        = 32,
    parameter int DEPTH_WORDS = 1024
) (
    input logic clk,
    input logic write_enable,
    input logic [XLEN-1:0] address,
    input logic [XLEN-1:0] write_data,
    output logic [XLEN-1:0] read_data
);

    logic [XLEN-1:0] memory[DEPTH_WORDS];
    logic [$clog2(DEPTH_WORDS)-1:0] word_address;

    assign word_address = address / INSTRUCTION_BYTES;

    /*
    * Asynchronous read
    */
    assign read_data    = memory[word_address];

    /*
    * Synchronous write
    */
    always_ff @(posedge clk) begin
        if (write_enable) begin
            memory[word_address] <= write_data;
        end else begin
            memory[word_address] <= memory[word_address];
        end
    end

endmodule

rtl/memory/instruction_rom.sv
import riscv_pkg::*;

module instruction_rom #(
    parameter int XLEN        = 32,
    parameter int DEPTH_WORDS = 1024
) (
    input logic [XLEN-1:0] address,
    output logic [INSTRUCTION_WIDTH-1:0] instruction
);
    /*
    * ROM storage
    */
    logic [INSTRUCTION_WIDTH-1:0] memory[DEPTH_WORDS];
    logic [$clog2(DEPTH_WORDS)-1:0] word_address;

    assign word_address = address / INSTRUCTION_BYTES;

    /*
    * Asynchronous read
    */
    assign instruction  = memory[word_address];

    /*
    * Load program at sim time
    */
    initial begin
        $readmemh("main.hex", memory);
    end

endmodule

rtl/core/core.sv
import riscv_pkg::*;

module core #(
    parameter int XLEN = 32
) (
    input logic clk,
    input logic n_rst,

    output logic [XLEN-1:0] program_counter,
    input logic [INSTRUCTION_WIDTH-1:0] instruction,

    output logic memory_write_enable,
    output logic [XLEN-1:0] memory_address,
    output logic [XLEN-1:0] memory_write_data,
    input logic [XLEN-1:0] memory_read_data
);

    /*
    * Architectural state
    */
    logic [XLEN-1:0] program_counter_next;
    logic [XLEN-1:0] registers[REGISTER_COUNT-1:0];
    logic [XLEN-1:0] registers_next[REGISTER_COUNT-1:0];

    /*
    * Decode
    */
    logic [OPCODE_FIELD_WIDTH-1:0] instruction_class;
    logic [REGISTER_INDEX_WIDTH-1:0] destination_register_index;
    logic [REGISTER_INDEX_WIDTH-1:0] source_register_1_index;
    logic [REGISTER_INDEX_WIDTH-1:0] source_register_2_index;

    /*
    * Immediate values
    */
    logic [XLEN-1:0] immediate_i;
    logic [XLEN-1:0] immediate_s;
    logic [XLEN-1:0] immediate_j;

    /*
    * Decode logic
    */
    assign instruction_class = instruction[OPCODE_MSB:OPCODE_LSB];
    assign destination_register_index = instruction[DEST_REG_MSB:DEST_REG_LSB];
    assign source_register_1_index = instruction[SRC_REG1_MSB:SRC_REG1_LSB];
    assign source_register_2_index = instruction[SRC_REG2_MSB:SRC_REG2_LSB];

    assign immediate_i = {{(XLEN - 12) {instruction[31]}}, instruction[31:20]};
    assign immediate_s = {{(XLEN - 12) {instruction[31]}}, instruction[31:25], instruction[11:7]};
    assign immediate_j = {
        {(XLEN - 12) {instruction[31]}}, instruction[19:12], instruction[20], instruction[30:21]
    };

    /*
    * Execute
    */
    always_comb begin
        // Default behavior
        program_counter_next = program_counter + INSTRUCTION_BYTES;
        for (int i = 0; i < REGISTER_COUNT; i++) begin
            registers_next[i] = registers[i];
        end
        memory_write_enable = 1'b0;
        memory_address      = '0;
        memory_write_data   = '0;

        // Instruction specific
        case (instruction_class)
            // Integer arithmetic with immediate
            CLASS_OP_IMM: begin
                registers_next[destination_register_index] = registers[source_register_1_index] + immediate_i;
            end
            // Jump and link
            CLASS_JAL: begin
                registers_next[destination_register_index] = program_counter + INSTRUCTION_BYTES;
                program_counter_next                       = program_counter + immediate_j;
            end
            // Store to memory
            CLASS_STORE: begin
                memory_write_enable = 1'b1;
                memory_address      = registers[source_register_1_index] + immediate_s;
                memory_write_data   = registers[source_register_2_index];
            end
            default: begin
                // nop
            end
        endcase

        // Enforce register X0 = 0
        registers_next[X0] = '0;
    end

    /*
    * Commit
    */
    always_ff @(posedge clk) begin
        if (~n_rst) begin
            program_counter <= '0;
            for (int i = 0; i < REGISTER_COUNT; i++) begin
                registers[i] <= '0;
            end
        end else begin
            program_counter <= program_counter_next;
            for (int i = 0; i < REGISTER_COUNT; i++) begin
                registers_next[i] <= registers[i];
            end
        end
    end

endmodule

rtl/top.sv
import riscv_pkg::*;

/**
* top.sv
* @brief Top-level definition for a simple RISC-V SoC.
*
* @param XLEN the SoC address bit width (32 or 64).
* @param clk the provided clock for the SoC.
* @param n_rst active low reset signal for the SoC.
*/
module top #(
    parameter int XLEN = 32
) (
    input logic clk,
    input logic n_rst
);
    logic [XLEN-1:0] program_counter;
    logic [INSTRUCTION_WIDTH-1:0] instruction;

    logic memory_write_enable;
    logic [XLEN-1:0] memory_address;
    logic [XLEN-1:0] memory_write_data;
    logic [XLEN-1:0] memory_read_data;

    /*
    * CPU
    */
    core cpu (
        .clk  (clk),
        .n_rst(n_rst),

        .program_counter(program_counter),
        .instruction    (instruction_register),

        .memory_write_enable(memory_write_enable),
        .memory_address     (memory_address),
        .memory_write_data  (memory_write_data),
        .memory_read_data   (memory_read_data)
    );

    /*
    * Memory
    */
    instruction_rom rom (
        .address    (program_counter),
        .instruction(instruction_register)
    );

    data_ram ram (
        .clk         (clk),
        .write_enable(memory_write_enable),
        .address     (memory_address),
        .write_data  (memory_write_data),
        .read_data   (memory_read_data)
    );

endmodule

sim/tb_top.sv
module tb_top;

    logic clk;
    logic n_rst;

    // Instantiate DUT
    top dut (
        .clk  (clk),
        .n_rst(n_rst)
    );

    //
    // Clock generation
    //
    initial begin
        clk = 0;
        forever #5 clk = ~clk;  // 100 MHz equivalent
    end

    //
    // Reset sequence
    //
    initial begin
        n_rst = 0;
        #20;
        n_rst = 1;
    end

    //
    // Simulation control
    //
    initial begin
        // Dump waves
        $dumpfile("wave.vcd");
        $dumpvars(0, dut);

        // Run long enough to execute program
        #1000;

        $finish;
    end

endmodule

sim/wave.vcd
$date
	Mon Dec 15 23:11:20 2025
$end
$version
	Icarus Verilog
$end
$timescale
	1s
$end
$scope module tb_top $end
$scope module dut $end
$var wire 1 ! clk $end
$var wire 1 " n_rst $end
$var wire 32 # program_counter [31:0] $end
$var wire 1 $ memory_write_enable $end
$var wire 32 % memory_write_data [31:0] $end
$var wire 32 & memory_read_data [31:0] $end
$var wire 32 ' memory_address [31:0] $end
$var wire 32 ( instruction [31:0] $end
$var parameter 32 ) XLEN $end
$scope module cpu $end
$var wire 1 ! clk $end
$var wire 1 " n_rst $end
$var wire 5 * source_register_2_index [4:0] $end
$var wire 5 + source_register_1_index [4:0] $end
$var wire 32 , memory_read_data [31:0] $end
$var wire 7 - instruction_class [6:0] $end
$var wire 32 . instruction [31:0] $end
$var wire 32 / immediate_s [31:0] $end
$var wire 32 0 immediate_j [31:0] $end
$var wire 32 1 immediate_i [31:0] $end
$var wire 5 2 destination_register_index [4:0] $end
$var parameter 32 3 XLEN $end
$var reg 32 4 memory_address [31:0] $end
$var reg 32 5 memory_write_data [31:0] $end
$var reg 1 $ memory_write_enable $end
$var reg 32 6 program_counter [31:0] $end
$var reg 32 7 program_counter_next [31:0] $end
$scope begin $ivl_for_loop0 $end
$var integer 32 8 i [31:0] $end
$upscope $end
$scope begin $ivl_for_loop1 $end
$var integer 32 9 i [31:0] $end
$upscope $end
$scope begin $ivl_for_loop2 $end
$var integer 32 : i [31:0] $end
$upscope $end
$upscope $end
$scope module ram $end
$var wire 32 ; address [31:0] $end
$var wire 1 ! clk $end
$var wire 32 < read_data [31:0] $end
$var wire 32 = write_data [31:0] $end
$var wire 1 $ write_enable $end
$var wire 10 > word_address [9:0] $end
$var parameter 32 ? DEPTH_WORDS $end
$var parameter 32 @ XLEN $end
$upscope $end
$scope module rom $end
$var wire 32 A address [31:0] $end
$var wire 32 B instruction [31:0] $end
$var wire 10 C word_address [9:0] $end
$var parameter 32 D DEPTH_WORDS $end
$var parameter 32 E XLEN $end
$upscope $end
$upscope $end
$upscope $end
$enddefinitions $end
$comment Show the parameter values. $end
$dumpall
b100000 E
b10000000000 D
b100000 @
b10000000000 ?
b100000 3
b100000 )
$end
#0
$dumpvars
bx C
bx B
bx A
b0 >
b0 =
bx <
b0 ;
b0 :
b0 9
b100000 8
bx 7
bx 6
b0 5
b0 4
bx 2
bx 1
bx 0
bx /
bx .
bx -
bx ,
bx +
bx *
bx (
b0 '
bx &
b0 %
0$
bx #
0"
0!
$end
#5
b0 0
b0 /
b0 1
b0 *
b0 +
b0 2
b10011 -
b100000 8
b100 7
b10011 (
b10011 .
b10011 B
b0 C
b0 #
b0 6
b0 A
b100000 9
1!
#10
0!
#15
b100000 9
1!
#20
0!
1"
#25
b1 -
b100000 8
b1000 7
b1 (
b1 .
b1 B
b1 C
b100 #
b100 6
b100 A
b100000 :
1!
#30
0!
#35
b1 /
b1 2
b1000000 -
b100000 8
b1100 7
b11000000 (
b11000000 .
b11000000 B
b10 C
b1000 #
b1000 6
b1000 A
b100000 :
1!
#40
0!
#45
b0 /
b0 2
b1000001 -
b100000 8
b10000 7
b1000001 (
b1000001 .
b1000001 B
b11 C
b1100 #
b1100 6
b1100 A
b100000 :
1!
#50
0!
#55
b1 /
b1 2
b1101111 -
b100000 8
b10100 7
b11101111 (
b11101111 .
b11101111 B
b100 C
b10000 #
b10000 6
b10000 A
b100000 :
1!
#60
0!
#65
b0 /
b0 2
b0 -
b100000 8
b11000 7
b0 (
b0 .
b0 B
b101 C
b10100 #
b10100 6
b10100 A
b100000 :
1!
#70
0!
#75
b1 /
b1 2
b100000 8
b11100 7
b10000000 (
b10000000 .
b10000000 B
b110 C
b11000 #
b11000 6
b11000 A
b100000 :
1!
#80
0!
#85
b0 /
b0 2
b100000 8
b100000 7
b0 (
b0 .
b0 B
b111 C
b11100 #
b11100 6
b11100 A
b100000 :
1!
#90
0!
#95
b1101111 -
b100000 8
b100100 7
b1101111 (
b1101111 .
b1101111 B
b1000 C
b100000 #
b100000 6
b100000 A
b100000 :
1!
#100
0!
#105
b0 -
b100000 8
b101000 7
b0 (
b0 .
b0 B
b1001 C
b100100 #
b100100 6
b100100 A
b100000 :
1!
#110
0!
#115
b100000 8
b101100 7
b1010 C
b101000 #
b101000 6
b101000 A
b100000 :
1!
#120
0!
#125
b100000 8
b110000 7
b1011 C
b101100 #
b101100 6
b101100 A
b100000 :
1!
#130
0!
#135
b10011 -
b100000 8
b110100 7
b10011 (
b10011 .
b10011 B
b1100 C
b110000 #
b110000 6
b110000 A
b100000 :
1!
#140
0!
#145
b1 -
b100000 8
b111000 7
b1 (
b1 .
b1 B
b1101 C
b110100 #
b110100 6
b110100 A
b100000 :
1!
#150
0!
#155
b100000 8
b111100 7
b1110 C
b111000 #
b111000 6
b111000 A
b100000 :
1!
#160
0!
#165
b1 /
b1 2
b1111111 -
b100000 8
b1000000 7
b11111111 (
b11111111 .
b11111111 B
b1111 C
b111100 #
b111100 6
b111100 A
b100000 :
1!
#170
0!
#175
b0 /
b0 2
b100011 -
b100000 8
b1000000 7
b100011 (
b100011 .
b100011 B
b10000 C
b1000000 #
b1000000 6
b1000000 A
b100000 :
1!
#180
0!
#185
b100000 :
1!
#190
0!
#195
b100000 :
1!
#200
0!
#205
b100000 :
1!
#210
0!
#215
b100000 :
1!
#220
0!
#225
b100000 :
1!
#230
0!
#235
b100000 :
1!
#240
0!
#245
b100000 :
1!
#250
0!
#255
b100000 :
1!
#260
0!
#265
b100000 :
1!
#270
0!
#275
b100000 :
1!
#280
0!
#285
b100000 :
1!
#290
0!
#295
b100000 :
1!
#300
0!
#305
b100000 :
1!
#310
0!
#315
b100000 :
1!
#320
0!
#325
b100000 :
1!
#330
0!
#335
b100000 :
1!
#340
0!
#345
b100000 :
1!
#350
0!
#355
b100000 :
1!
#360
0!
#365
b100000 :
1!
#370
0!
#375
b100000 :
1!
#380
0!
#385
b100000 :
1!
#390
0!
#395
b100000 :
1!
#400
0!
#405
b100000 :
1!
#410
0!
#415
b100000 :
1!
#420
0!
#425
b100000 :
1!
#430
0!
#435
b100000 :
1!
#440
0!
#445
b100000 :
1!
#450
0!
#455
b100000 :
1!
#460
0!
#465
b100000 :
1!
#470
0!
#475
b100000 :
1!
#480
0!
#485
b100000 :
1!
#490
0!
#495
b100000 :
1!
#500
0!
#505
b100000 :
1!
#510
0!
#515
b100000 :
1!
#520
0!
#525
b100000 :
1!
#530
0!
#535
b100000 :
1!
#540
0!
#545
b100000 :
1!
#550
0!
#555
b100000 :
1!
#560
0!
#565
b100000 :
1!
#570
0!
#575
b100000 :
1!
#580
0!
#585
b100000 :
1!
#590
0!
#595
b100000 :
1!
#600
0!
#605
b100000 :
1!
#610
0!
#615
b100000 :
1!
#620
0!
#625
b100000 :
1!
#630
0!
#635
b100000 :
1!
#640
0!
#645
b100000 :
1!
#650
0!
#655
b100000 :
1!
#660
0!
#665
b100000 :
1!
#670
0!
#675
b100000 :
1!
#680
0!
#685
b100000 :
1!
#690
0!
#695
b100000 :
1!
#700
0!
#705
b100000 :
1!
#710
0!
#715
b100000 :
1!
#720
0!
#725
b100000 :
1!
#730
0!
#735
b100000 :
1!
#740
0!
#745
b100000 :
1!
#750
0!
#755
b100000 :
1!
#760
0!
#765
b100000 :
1!
#770
0!
#775
b100000 :
1!
#780
0!
#785
b100000 :
1!
#790
0!
#795
b100000 :
1!
#800
0!
#805
b100000 :
1!
#810
0!
#815
b100000 :
1!
#820
0!
#825
b100000 :
1!
#830
0!
#835
b100000 :
1!
#840
0!
#845
b100000 :
1!
#850
0!
#855
b100000 :
1!
#860
0!
#865
b100000 :
1!
#870
0!
#875
b100000 :
1!
#880
0!
#885
b100000 :
1!
#890
0!
#895
b100000 :
1!
#900
0!
#905
b100000 :
1!
#910
0!
#915
b100000 :
1!
#920
0!
#925
b100000 :
1!
#930
0!
#935
b100000 :
1!
#940
0!
#945
b100000 :
1!
#950
0!
#955
b100000 :
1!
#960
0!
#965
b100000 :
1!
#970
0!
#975
b100000 :
1!
#980
0!
#985
b100000 :
1!
#990
0!
#995
b100000 :
1!
