misc/test/alu/alu.sv
module adder #(
  parameter WIDTH
)(
  input logic [WIDTH-1:0] a, b,
  output logic [WIDTH-1:0] result
);

  assign result = a + b;

endmodule

src/tb_alu.sv
module tb_adder ();

  // Constants definition
  localparam WIDTH = 8;

  // Inputs
  logic [WIDTH-1:0] a, b;

  // Outputs
  logic [WIDTH-1:0] result;

  // Device under test
  adder #(
    .WIDTH(WIDTH)
  ) dut (
    .a(a),
    .b(b),
    .result(result)
  );

  // File dump
  initial begin
    $dumpfile("tb_adder.vcd");
    $dumpvars(0, tb_adder);
  end

  // Test sequence
  initial begin
    a = 0;
    b = 0;
  
    for (int i = 0; i < 2**WIDTH; i++) begin
      for (int j = 0; j < 2**WIDTH; j++) begin
        #1 b = j;
        if (result !== a + b) begin
          $error("Adder error at: a = %h, b = %h", a, b);
        end
      end
      #1 a = i;
    end

    $finish;  
  end

endmodule

src/tb_adder.vcd
$date
	Thu Oct 16 17:19:46 2025
$end
$version
	Icarus Verilog
$end
$timescale
	1s
$end
$scope module tb_adder $end
$var wire 8 ! result [7:0] $end
$var parameter 32 " WIDTH $end
$var reg 8 # a [7:0] $end
$var reg 8 $ b [7:0] $end
$scope module dut $end
$var wire 8 % a [7:0] $end
$var wire 8 & b [7:0] $end
$var wire 8 ' result [7:0] $end
$var parameter 32 ( WIDTH $end
$upscope $end
$scope begin $ivl_for_loop0 $end
$var integer 32 ) i [31:0] $end
$scope begin $ivl_for_loop1 $end
$var integer 32 * j [31:0] $end
$upscope $end
$upscope $end
$upscope $end
$enddefinitions $end
$comment Show the parameter values. $end
$dumpall
b1000 (
b1000 "
$end
#0
$dumpvars
b0 *
b0 )
b0 '
b0 &
b0 %
b0 $
b0 #
b0 !
$end
#1
b1 *
#2
b10 *
b1 !
b1 '
b1 $
b1 &
#3
b11 *
b10 !
b10 '
b10 $
b10 &
#4
b100 *
b11 !
b11 '
b11 $
b11 &
#5
b101 *
b100 !
b100 '
b100 $
b100 &
#6
b110 *
b101 !
b101 '
b101 $
b101 &
#7
b111 *
b110 !
b110 '
b110 $
b110 &
#8
b1000 *
b111 !
b111 '
b111 $
b111 &
#9
b1001 *
b1000 !
b1000 '
b1000 $
b1000 &
#10
b1010 *
b1001 !
b1001 '
b1001 $
b1001 &
#11
b1011 *
b1010 !
b1010 '
b1010 $
b1010 &
#12
b1100 *
b1011 !
b1011 '
b1011 $
b1011 &
#13
b1101 *
b1100 !
b1100 '
b1100 $
b1100 &
#14
b1110 *
b1101 !
b1101 '
b1101 $
b1101 &
#15
b1111 *
b1110 !
b1110 '
b1110 $
b1110 &
#16
b10000 *
b1111 !
b1111 '
b1111 $
b1111 &
#17
b10001 *
b10000 !
b10000 '
b10000 $
b10000 &
#18
b10010 *
b10001 !
b10001 '
b10001 $
b10001 &
#19
b10011 *
b10010 !
b10010 '
b10010 $
b10010 &
#20
b10100 *
b10011 !
b10011 '
b10011 $
b10011 &
#21
b10101 *
b10100 !
b10100 '
b10100 $
b10100 &
#22
b10110 *
b10101 !
b10101 '
b10101 $
b10101 &
#23
b10111 *
b10110 !
b10110 '
b10110 $
b10110 &
#24
b11000 *
b10111 !
b10111 '
b10111 $
b10111 &
#25
b11001 *
b11000 !
b11000 '
b11000 $
b11000 &
#26
b11010 *
b11001 !
b11001 '
b11001 $
b11001 &
#27
b11011 *
b11010 !
b11010 '
b11010 $
b11010 &
#28
b11100 *
b11011 !
b11011 '
b11011 $
b11011 &
#29
b11101 *
b11100 !
b11100 '
b11100 $
b11100 &
#30
b11110 *
b11101 !
b11101 '
b11101 $
b11101 &
#31
b11111 *
b11110 !
b11110 '
b11110 $
b11110 &
#32
b100000 *
b11111 !
b11111 '
b11111 $
b11111 &
#33
b100001 *
b100000 !
b100000 '
b100000 $
b100000 &
#34
b100010 *
b100001 !
b100001 '
b100001 $
b100001 &
#35
b100011 *
b100010 !
b100010 '
b100010 $
b100010 &
#36
b100100 *
b100011 !
b100011 '
b100011 $
b100011 &
#37
b100101 *
b100100 !
b100100 '
b100100 $
b100100 &
#38
b100110 *
b100101 !
b100101 '
b100101 $
b100101 &
#39
b100111 *
b100110 !
b100110 '
b100110 $
b100110 &
#40
b101000 *
b100111 !
b100111 '
b100111 $
b100111 &
#41
b101001 *
b101000 !
b101000 '
b101000 $
b101000 &
#42
b101010 *
b101001 !
b101001 '
b101001 $
b101001 &
#43
b101011 *
b101010 !
b101010 '
b101010 $
b101010 &
#44
b101100 *
b101011 !
b101011 '
b101011 $
b101011 &
#45
b101101 *
b101100 !
b101100 '
b101100 $
b101100 &
#46
b101110 *
b101101 !
b101101 '
b101101 $
b101101 &
#47
b101111 *
b101110 !
b101110 '
b101110 $
b101110 &
#48
b110000 *
b101111 !
b101111 '
b101111 $
b101111 &
#49
b110001 *
b110000 !
b110000 '
b110000 $
b110000 &
#50
b110010 *
b110001 !
b110001 '
b110001 $
b110001 &
#51
b110011 *
b110010 !
b110010 '
b110010 $
b110010 &
#52
b110100 *
b110011 !
b110011 '
b110011 $
b110011 &
#53
b110101 *
b110100 !
b110100 '
b110100 $
b110100 &
#54
b110110 *
b110101 !
b110101 '
b110101 $
b110101 &
#55
b110111 *
b110110 !
b110110 '
b110110 $
b110110 &
#56
b111000 *
b110111 !
b110111 '
b110111 $
b110111 &
#57
b111001 *
b111000 !
b111000 '
b111000 $
b111000 &
#58
b111010 *
b111001 !
b111001 '
b111001 $
b111001 &
#59
b111011 *
b111010 !
b111010 '
b111010 $
b111010 &
#60
b111100 *
b111011 !
b111011 '
b111011 $
b111011 &
#61
b111101 *
b111100 !
b111100 '
b111100 $
b111100 &
#62
b111110 *
b111101 !
b111101 '
b111101 $
b111101 &
#63
b111111 *
b111110 !
b111110 '
b111110 $
b111110 &
#64
b1000000 *
b111111 !
b111111 '
b111111 $
b111111 &
#65
b1000001 *
b1000000 !
b1000000 '
b1000000 $
b1000000 &
#66
b1000010 *
b1000001 !
b1000001 '
b1000001 $
b1000001 &
#67
b1000011 *
b1000010 !
b1000010 '
b1000010 $
b1000010 &
#68
b1000100 *
b1000011 !
b1000011 '
b1000011 $
b1000011 &
#69
b1000101 *
b1000100 !
b1000100 '
b1000100 $
b1000100 &
#70
b1000110 *
b1000101 !
b1000101 '
b1000101 $
b1000101 &
#71
b1000111 *
b1000110 !
b1000110 '
b1000110 $
b1000110 &
#72
b1001000 *
b1000111 !
b1000111 '
b1000111 $
b1000111 &
#73
b1001001 *
b1001000 !
b1001000 '
b1001000 $
b1001000 &
#74
b1001010 *
b1001001 !
b1001001 '
b1001001 $
b1001001 &
#75
b1001011 *
b1001010 !
b1001010 '
b1001010 $
b1001010 &
#76
b1001100 *
b1001011 !
b1001011 '
b1001011 $
b1001011 &
#77
b1001101 *
b1001100 !
b1001100 '
b1001100 $
b1001100 &
#78
b1001110 *
b1001101 !
b1001101 '
b1001101 $
b1001101 &
#79
b1001111 *
b1001110 !
b1001110 '
b1001110 $
b1001110 &
#80
b1010000 *
b1001111 !
b1001111 '
b1001111 $
b1001111 &
#81
b1010001 *
b1010000 !
b1010000 '
b1010000 $
b1010000 &
#82
b1010010 *
b1010001 !
b1010001 '
b1010001 $
b1010001 &
#83
b1010011 *
b1010010 !
b1010010 '
b1010010 $
b1010010 &
#84
b1010100 *
b1010011 !
b1010011 '
b1010011 $
b1010011 &
#85
b1010101 *
b1010100 !
b1010100 '
b1010100 $
b1010100 &
#86
b1010110 *
b1010101 !
b1010101 '
b1010101 $
b1010101 &
#87
b1010111 *
b1010110 !
b1010110 '
b1010110 $
b1010110 &
#88
b1011000 *
b1010111 !
b1010111 '
b1010111 $
b1010111 &
#89
b1011001 *
b1011000 !
b1011000 '
b1011000 $
b1011000 &
#90
b1011010 *
b1011001 !
b1011001 '
b1011001 $
b1011001 &
#91
b1011011 *
b1011010 !
b1011010 '
b1011010 $
b1011010 &
#92
b1011100 *
b1011011 !
b1011011 '
b1011011 $
b1011011 &
#93
b1011101 *
b1011100 !
b1011100 '
b1011100 $
b1011100 &
#94
b1011110 *
b1011101 !
b1011101 '
b1011101 $
b1011101 &
#95
b1011111 *
b1011110 !
b1011110 '
b1011110 $
b1011110 &
#96
b1100000 *
b1011111 !
b1011111 '
b1011111 $
b1011111 &
#97
b1100001 *
b1100000 !
b1100000 '
b1100000 $
b1100000 &
#98
b1100010 *
b1100001 !
b1100001 '
b1100001 $
b1100001 &
#99
b1100011 *
b1100010 !
b1100010 '
b1100010 $
b1100010 &
#100
b1100100 *
b1100011 !
b1100011 '
b1100011 $
b1100011 &
#101
b1100101 *
b1100100 !
b1100100 '
b1100100 $
b1100100 &
#102
b1100110 *
b1100101 !
b1100101 '
b1100101 $
b1100101 &
#103
b1100111 *
b1100110 !
b1100110 '
b1100110 $
b1100110 &
#104
b1101000 *
b1100111 !
b1100111 '
b1100111 $
b1100111 &
#105
b1101001 *
b1101000 !
b1101000 '
b1101000 $
b1101000 &
#106
b1101010 *
b1101001 !
b1101001 '
b1101001 $
b1101001 &
#107
b1101011 *
b1101010 !
b1101010 '
b1101010 $
b1101010 &
#108
b1101100 *
b1101011 !
b1101011 '
b1101011 $
b1101011 &
#109
b1101101 *
b1101100 !
b1101100 '
b1101100 $
b1101100 &
#110
b1101110 *
b1101101 !
b1101101 '
b1101101 $
b1101101 &
#111
b1101111 *
b1101110 !
b1101110 '
b1101110 $
b1101110 &
#112
b1110000 *
b1101111 !
b1101111 '
b1101111 $
b1101111 &
#113
b1110001 *
b1110000 !
b1110000 '
b1110000 $
b1110000 &
#114
b1110010 *
b1110001 !
b1110001 '
b1110001 $
b1110001 &
#115
b1110011 *
b1110010 !
b1110010 '
b1110010 $
b1110010 &
#116
b1110100 *
b1110011 !
b1110011 '
b1110011 $
b1110011 &
#117
b1110101 *
b1110100 !
b1110100 '
b1110100 $
b1110100 &
#118
b1110110 *
b1110101 !
b1110101 '
b1110101 $
b1110101 &
#119
b1110111 *
b1110110 !
b1110110 '
b1110110 $
b1110110 &
#120
b1111000 *
b1110111 !
b1110111 '
b1110111 $
b1110111 &
#121
b1111001 *
b1111000 !
b1111000 '
b1111000 $
b1111000 &
#122
b1111010 *
b1111001 !
b1111001 '
b1111001 $
b1111001 &
#123
b1111011 *
b1111010 !
b1111010 '
b1111010 $
b1111010 &
#124
b1111100 *
b1111011 !
b1111011 '
b1111011 $
b1111011 &
#125
b1111101 *
b1111100 !
b1111100 '
b1111100 $
b1111100 &
#126
b1111110 *
b1111101 !
b1111101 '
b1111101 $
b1111101 &
#127
b1111111 *
b1111110 !
b1111110 '
b1111110 $
b1111110 &
#128
b10000000 *
b1111111 !
b1111111 '
b1111111 $
b1111111 &
#129
b10000001 *
b10000000 !
b10000000 '
b10000000 $
b10000000 &
#130
b10000010 *
b10000001 !
b10000001 '
b10000001 $
b10000001 &
#131
b10000011 *
b10000010 !
b10000010 '
b10000010 $
b10000010 &
#132
b10000100 *
b10000011 !
b10000011 '
b10000011 $
b10000011 &
#133
b10000101 *
b10000100 !
b10000100 '
b10000100 $
b10000100 &
#134
b10000110 *
b10000101 !
b10000101 '
b10000101 $
b10000101 &
#135
b10000111 *
b10000110 !
b10000110 '
b10000110 $
b10000110 &
#136
b10001000 *
b10000111 !
b10000111 '
b10000111 $
b10000111 &
#137
b10001001 *
b10001000 !
b10001000 '
b10001000 $
b10001000 &
#138
b10001010 *
b10001001 !
b10001001 '
b10001001 $
b10001001 &
#139
b10001011 *
b10001010 !
b10001010 '
b10001010 $
b10001010 &
#140
b10001100 *
b10001011 !
b10001011 '
b10001011 $
b10001011 &
#141
b10001101 *
b10001100 !
b10001100 '
b10001100 $
b10001100 &
#142
b10001110 *
b10001101 !
b10001101 '
b10001101 $
b10001101 &
#143
b10001111 *
b10001110 !
b10001110 '
b10001110 $
b10001110 &
#144
b10010000 *
b10001111 !
b10001111 '
b10001111 $
b10001111 &
#145
b10010001 *
b10010000 !
b10010000 '
b10010000 $
b10010000 &
#146
b10010010 *
b10010001 !
b10010001 '
b10010001 $
b10010001 &
#147
b10010011 *
b10010010 !
b10010010 '
b10010010 $
b10010010 &
#148
b10010100 *
b10010011 !
b10010011 '
b10010011 $
b10010011 &
#149
b10010101 *
b10010100 !
b10010100 '
b10010100 $
b10010100 &
#150
b10010110 *
b10010101 !
b10010101 '
b10010101 $
b10010101 &
#151
b10010111 *
b10010110 !
b10010110 '
b10010110 $
b10010110 &
#152
b10011000 *
b10010111 !
b10010111 '
b10010111 $
b10010111 &
#153
b10011001 *
b10011000 !
b10011000 '
b10011000 $
b10011000 &
#154
b10011010 *
b10011001 !
b10011001 '
b10011001 $
b10011001 &
#155
b10011011 *
b10011010 !
b10011010 '
b10011010 $
b10011010 &
#156
b10011100 *
b10011011 !
b10011011 '
b10011011 $
b10011011 &
#157
b10011101 *
b10011100 !
b10011100 '
b10011100 $
b10011100 &
#158
b10011110 *
b10011101 !
b10011101 '
b10011101 $
b10011101 &
#159
b10011111 *
b10011110 !
b10011110 '
b10011110 $
b10011110 &
#160
b10100000 *
b10011111 !
b10011111 '
b10011111 $
b10011111 &
#161
b10100001 *
b10100000 !
b10100000 '
b10100000 $
b10100000 &
#162
b10100010 *
b10100001 !
b10100001 '
b10100001 $
b10100001 &
#163
b10100011 *
b10100010 !
b10100010 '
b10100010 $
b10100010 &
#164
b10100100 *
b10100011 !
b10100011 '
b10100011 $
b10100011 &
#165
b10100101 *
b10100100 !
b10100100 '
b10100100 $
b10100100 &
#166
b10100110 *
b10100101 !
b10100101 '
b10100101 $
b10100101 &
#167
b10100111 *
b10100110 !
b10100110 '
b10100110 $
b10100110 &
#168
b10101000 *
b10100111 !
b10100111 '
b10100111 $
b10100111 &
#169
b10101001 *
b10101000 !
b10101000 '
b10101000 $
b10101000 &
#170
b10101010 *
b10101001 !
b10101001 '
b10101001 $
b10101001 &
#171
b10101011 *
b10101010 !
b10101010 '
b10101010 $
b10101010 &
#172
b10101100 *
b10101011 !
b10101011 '
b10101011 $
b10101011 &
#173
b10101101 *
b10101100 !
b10101100 '
b10101100 $
b10101100 &
#174
b10101110 *
b10101101 !
b10101101 '
b10101101 $
b10101101 &
#175
b10101111 *
b10101110 !
b10101110 '
b10101110 $
b10101110 &
#176
b10110000 *
b10101111 !
b10101111 '
b10101111 $
b10101111 &
#177
b10110001 *
b10110000 !
b10110000 '
b10110000 $
b10110000 &
#178
b10110010 *
b10110001 !
b10110001 '
b10110001 $
b10110001 &
#179
b10110011 *
b10110010 !
b10110010 '
b10110010 $
b10110010 &
#180
b10110100 *
b10110011 !
b10110011 '
b10110011 $
b10110011 &
#181
b10110101 *
b10110100 !
b10110100 '
b10110100 $
b10110100 &
#182
b10110110 *
b10110101 !
b10110101 '
b10110101 $
b10110101 &
#183
b10110111 *
b10110110 !
b10110110 '
b10110110 $
b10110110 &
#184
b10111000 *
b10110111 !
b10110111 '
b10110111 $
b10110111 &
#185
b10111001 *
b10111000 !
b10111000 '
b10111000 $
b10111000 &
#186
b10111010 *
b10111001 !
b10111001 '
b10111001 $
b10111001 &
#187
b10111011 *
b10111010 !
b10111010 '
b10111010 $
b10111010 &
#188
b10111100 *
b10111011 !
b10111011 '
b10111011 $
b10111011 &
#189
b10111101 *
b10111100 !
b10111100 '
b10111100 $
b10111100 &
#190
b10111110 *
b10111101 !
b10111101 '
b10111101 $
b10111101 &
#191
b10111111 *
b10111110 !
b10111110 '
b10111110 $
b10111110 &
#192
b11000000 *
b10111111 !
b10111111 '
b10111111 $
b10111111 &
#193
b11000001 *
b11000000 !
b11000000 '
b11000000 $
b11000000 &
#194
b11000010 *
b11000001 !
b11000001 '
b11000001 $
b11000001 &
#195
b11000011 *
b11000010 !
b11000010 '
b11000010 $
b11000010 &
#196
b11000100 *
b11000011 !
b11000011 '
b11000011 $
b11000011 &
#197
b11000101 *
b11000100 !
b11000100 '
b11000100 $
b11000100 &
#198
b11000110 *
b11000101 !
b11000101 '
b11000101 $
b11000101 &
#199
b11000111 *
b11000110 !
b11000110 '
b11000110 $
b11000110 &
#200
b11001000 *
b11000111 !
b11000111 '
b11000111 $
b11000111 &
#201
b11001001 *
b11001000 !
b11001000 '
b11001000 $
b11001000 &
#202
b11001010 *
b11001001 !
b11001001 '
b11001001 $
b11001001 &
#203
b11001011 *
b11001010 !
b11001010 '
b11001010 $
b11001010 &
#204
b11001100 *
b11001011 !
b11001011 '
b11001011 $
b11001011 &
#205
b11001101 *
b11001100 !
b11001100 '
b11001100 $
b11001100 &
#206
b11001110 *
b11001101 !
b11001101 '
b11001101 $
b11001101 &
#207
b11001111 *
b11001110 !
b11001110 '
b11001110 $
b11001110 &
#208
b11010000 *
b11001111 !
b11001111 '
b11001111 $
b11001111 &
#209
b11010001 *
b11010000 !
b11010000 '
b11010000 $
b11010000 &
#210
b11010010 *
b11010001 !
b11010001 '
b11010001 $
b11010001 &
#211
b11010011 *
b11010010 !
b11010010 '
b11010010 $
b11010010 &
#212
b11010100 *
b11010011 !
b11010011 '
b11010011 $
b11010011 &
#213
b11010101 *
b11010100 !
b11010100 '
b11010100 $
b11010100 &
#214
b11010110 *
b11010101 !
b11010101 '
b11010101 $
b11010101 &
#215
b11010111 *
b11010110 !
b11010110 '
b11010110 $
b11010110 &
#216
b11011000 *
b11010111 !
b11010111 '
b11010111 $
b11010111 &
#217
b11011001 *
b11011000 !
b11011000 '
b11011000 $
b11011000 &
#218
b11011010 *
b11011001 !
b11011001 '
b11011001 $
b11011001 &
#219
b11011011 *
b11011010 !
b11011010 '
b11011010 $
b11011010 &
#220
b11011100 *
b11011011 !
b11011011 '
b11011011 $
b11011011 &
#221
b11011101 *
b11011100 !
b11011100 '
b11011100 $
b11011100 &
#222
b11011110 *
b11011101 !
b11011101 '
b11011101 $
b11011101 &
#223
b11011111 *
b11011110 !
b11011110 '
b11011110 $
b11011110 &
#224
b11100000 *
b11011111 !
b11011111 '
b11011111 $
b11011111 &
#225
b11100001 *
b11100000 !
b11100000 '
b11100000 $
b11100000 &
#226
b11100010 *
b11100001 !
b11100001 '
b11100001 $
b11100001 &
#227
b11100011 *
b11100010 !
b11100010 '
b11100010 $
b11100010 &
#228
b11100100 *
b11100011 !
b11100011 '
b11100011 $
b11100011 &
#229
b11100101 *
b11100100 !
b11100100 '
b11100100 $
b11100100 &
#230
b11100110 *
b11100101 !
b11100101 '
b11100101 $
b11100101 &
#231
b11100111 *
b11100110 !
b11100110 '
b11100110 $
b11100110 &
#232
b11101000 *
b11100111 !
b11100111 '
b11100111 $
b11100111 &
#233
b11101001 *
b11101000 !
b11101000 '
b11101000 $
b11101000 &
#234
b11101010 *
b11101001 !
b11101001 '
b11101001 $
b11101001 &
#235
b11101011 *
b11101010 !
b11101010 '
b11101010 $
b11101010 &
#236
b11101100 *
b11101011 !
b11101011 '
b11101011 $
b11101011 &
#237
b11101101 *
b11101100 !
b11101100 '
b11101100 $
b11101100 &
#238
b11101110 *
b11101101 !
b11101101 '
b11101101 $
b11101101 &
#239
b11101111 *
b11101110 !
b11101110 '
b11101110 $
b11101110 &
#240
b11110000 *
b11101111 !
b11101111 '
b11101111 $
b11101111 &
#241
b11110001 *
b11110000 !
b11110000 '
b11110000 $
b11110000 &
#242
b11110010 *
b11110001 !
b11110001 '
b11110001 $
b11110001 &
#243
b11110011 *
b11110010 !
b11110010 '
b11110010 $
b11110010 &
#244
b11110100 *
b11110011 !
b11110011 '
b11110011 $
b11110011 &
#245
b11110101 *
b11110100 !
b11110100 '
b11110100 $
b11110100 &
#246
b11110110 *
b11110101 !
b11110101 '
b11110101 $
b11110101 &
#247
b11110111 *
b11110110 !
b11110110 '
b11110110 $
b11110110 &
#248
b11111000 *
b11110111 !
b11110111 '
b11110111 $
b11110111 &
#249
b11111001 *
b11111000 !
b11111000 '
b11111000 $
b11111000 &
#250
b11111010 *
b11111001 !
b11111001 '
b11111001 $
b11111001 &
#251
b11111011 *
b11111010 !
b11111010 '
b11111010 $
b11111010 &
#252
b11111100 *
b11111011 !
b11111011 '
b11111011 $
b11111011 &
#253
b11111101 *
b11111100 !
b11111100 '
b11111100 $
b11111100 &
#254
b11111110 *
b11111101 !
b11111101 '
b11111101 $
b11111101 &
#255
b11111111 *
b11111110 !
b11111110 '
b11111110 $
b11111110 &
#256
b100000000 *
b11111111 !
b11111111 '
b11111111 $
b11111111 &
#257
b0 *
b1 )
#258
b1 *
b0 !
b0 '
b0 $
b0 &
#259
b10 *
b1 !
b1 '
b1 $
b1 &
#260
b11 *
b10 !
b10 '
b10 $
b10 &
#261
b100 *
b11 !
b11 '
b11 $
b11 &
#262
b101 *
b100 !
b100 '
b100 $
b100 &
#263
b110 *
b101 !
b101 '
b101 $
b101 &
#264
b111 *
b110 !
b110 '
b110 $
b110 &
#265
b1000 *
b111 !
b111 '
b111 $
b111 &
#266
b1001 *
b1000 !
b1000 '
b1000 $
b1000 &
#267
b1010 *
b1001 !
b1001 '
b1001 $
b1001 &
#268
b1011 *
b1010 !
b1010 '
b1010 $
b1010 &
#269
b1100 *
b1011 !
b1011 '
b1011 $
b1011 &
#270
b1101 *
b1100 !
b1100 '
b1100 $
b1100 &
#271
b1110 *
b1101 !
b1101 '
b1101 $
b1101 &
#272
b1111 *
b1110 !
b1110 '
b1110 $
b1110 &
#273
b10000 *
b1111 !
b1111 '
b1111 $
b1111 &
#274
b10001 *
b10000 !
b10000 '
b10000 $
b10000 &
#275
b10010 *
b10001 !
b10001 '
b10001 $
b10001 &
#276
b10011 *
b10010 !
b10010 '
b10010 $
b10010 &
#277
b10100 *
b10011 !
b10011 '
b10011 $
b10011 &
#278
b10101 *
b10100 !
b10100 '
b10100 $
b10100 &
#279
b10110 *
b10101 !
b10101 '
b10101 $
b10101 &
#280
b10111 *
b10110 !
b10110 '
b10110 $
b10110 &
#281
b11000 *
b10111 !
b10111 '
b10111 $
b10111 &
#282
b11001 *
b11000 !
b11000 '
b11000 $
b11000 &
#283
b11010 *
b11001 !
b11001 '
b11001 $
b11001 &
#284
b11011 *
b11010 !
b11010 '
b11010 $
b11010 &
#285
b11100 *
b11011 !
b11011 '
b11011 $
b11011 &
#286
b11101 *
b11100 !
b11100 '
b11100 $
b11100 &
#287
b11110 *
b11101 !
b11101 '
b11101 $
b11101 &
#288
b11111 *
b11110 !
b11110 '
b11110 $
b11110 &
#289
b100000 *
b11111 !
b11111 '
b11111 $
b11111 &
#290
b100001 *
b100000 !
b100000 '
b100000 $
b100000 &
#291
b100010 *
b100001 !
b100001 '
b100001 $
b100001 &
#292
b100011 *
b100010 !
b100010 '
b100010 $
b100010 &
#293
b100100 *
b100011 !
b100011 '
b100011 $
b100011 &
#294
b100101 *
b100100 !
b100100 '
b100100 $
b100100 &
#295
b100110 *
b100101 !
b100101 '
b100101 $
b100101 &
#296
b100111 *
b100110 !
b100110 '
b100110 $
b100110 &
#297
b101000 *
b100111 !
b100111 '
b100111 $
b100111 &
#298
b101001 *
b101000 !
b101000 '
b101000 $
b101000 &
#299
b101010 *
b101001 !
b101001 '
b101001 $
b101001 &
#300
b101011 *
b101010 !
b101010 '
b101010 $
b101010 &
#301
b101100 *
b101011 !
b101011 '
b101011 $
b101011 &
#302
b101101 *
b101100 !
b101100 '
b101100 $
b101100 &
#303
b101110 *
b101101 !
b101101 '
b101101 $
b101101 &
#304
b101111 *
b101110 !
b101110 '
b101110 $
b101110 &
#305
b110000 *
b101111 !
b101111 '
b101111 $
b101111 &
#306
b110001 *
b110000 !
b110000 '
b110000 $
b110000 &
#307
b110010 *
b110001 !
b110001 '
b110001 $
b110001 &
#308
b110011 *
b110010 !
b110010 '
b110010 $
b110010 &
#309
b110100 *
b110011 !
b110011 '
b110011 $
b110011 &
#310
b110101 *
b110100 !
b110100 '
b110100 $
b110100 &
#311
b110110 *
b110101 !
b110101 '
b110101 $
b110101 &
#312
b110111 *
b110110 !
b110110 '
b110110 $
b110110 &
#313
b111000 *
b110111 !
b110111 '
b110111 $
b110111 &
#314
b111001 *
b111000 !
b111000 '
b111000 $
b111000 &
#315
b111010 *
b111001 !
b111001 '
b111001 $
b111001 &
#316
b111011 *
b111010 !
b111010 '
b111010 $
b111010 &
#317
b111100 *
b111011 !
b111011 '
b111011 $
b111011 &
#318
b111101 *
b111100 !
b111100 '
b111100 $
b111100 &
#319
b111110 *
b111101 !
b111101 '
b111101 $
b111101 &
#320
b111111 *
b111110 !
b111110 '
b111110 $
b111110 &
#321
b1000000 *
b111111 !
b111111 '
b111111 $
b111111 &
#322
b1000001 *
b1000000 !
b1000000 '
b1000000 $
b1000000 &
#323
b1000010 *
b1000001 !
b1000001 '
b1000001 $
b1000001 &
#324
b1000011 *
b1000010 !
b1000010 '
b1000010 $
b1000010 &
#325
b1000100 *
b1000011 !
b1000011 '
b1000011 $
b1000011 &
#326
b1000101 *
b1000100 !
b1000100 '
b1000100 $
b1000100 &
#327
b1000110 *
b1000101 !
b1000101 '
b1000101 $
b1000101 &
#328
b1000111 *
b1000110 !
b1000110 '
b1000110 $
b1000110 &
#329
b1001000 *
b1000111 !
b1000111 '
b1000111 $
b1000111 &
#330
b1001001 *
b1001000 !
b1001000 '
b1001000 $
b1001000 &
#331
b1001010 *
b1001001 !
b1001001 '
b1001001 $
b1001001 &
#332
b1001011 *
b1001010 !
b1001010 '
b1001010 $
b1001010 &
#333
b1001100 *
b1001011 !
b1001011 '
b1001011 $
b1001011 &
#334
b1001101 *
b1001100 !
b1001100 '
b1001100 $
b1001100 &
#335
b1001110 *
b1001101 !
b1001101 '
b1001101 $
b1001101 &
#336
b1001111 *
b1001110 !
b1001110 '
b1001110 $
b1001110 &
#337
b1010000 *
b1001111 !
b1001111 '
b1001111 $
b1001111 &
#338
b1010001 *
b1010000 !
b1010000 '
b1010000 $
b1010000 &
#339
b1010010 *
b1010001 !
b1010001 '
b1010001 $
b1010001 &
#340
b1010011 *
b1010010 !
b1010010 '
b1010010 $
b1010010 &
#341
b1010100 *
b1010011 !
b1010011 '
b1010011 $
b1010011 &
#342
b1010101 *
b1010100 !
b1010100 '
b1010100 $
b1010100 &
#343
b1010110 *
b1010101 !
b1010101 '
b1010101 $
b1010101 &
#344
b1010111 *
b1010110 !
b1010110 '
b1010110 $
b1010110 &
#345
b1011000 *
b1010111 !
b1010111 '
b1010111 $
b1010111 &
#346
b1011001 *
b1011000 !
b1011000 '
b1011000 $
b1011000 &
#347
b1011010 *
b1011001 !
b1011001 '
b1011001 $
b1011001 &
#348
b1011011 *
b1011010 !
b1011010 '
b1011010 $
b1011010 &
#349
b1011100 *
b1011011 !
b1011011 '
b1011011 $
b1011011 &
#350
b1011101 *
b1011100 !
b1011100 '
b1011100 $
b1011100 &
#351
b1011110 *
b1011101 !
b1011101 '
b1011101 $
b1011101 &
#352
b1011111 *
b1011110 !
b1011110 '
b1011110 $
b1011110 &
#353
b1100000 *
b1011111 !
b1011111 '
b1011111 $
b1011111 &
#354
b1100001 *
b1100000 !
b1100000 '
b1100000 $
b1100000 &
#355
b1100010 *
b1100001 !
b1100001 '
b1100001 $
b1100001 &
#356
b1100011 *
b1100010 !
b1100010 '
b1100010 $
b1100010 &
#357
b1100100 *
b1100011 !
b1100011 '
b1100011 $
b1100011 &
#358
b1100101 *
b1100100 !
b1100100 '
b1100100 $
b1100100 &
#359
b1100110 *
b1100101 !
b1100101 '
b1100101 $
b1100101 &
#360
b1100111 *
b1100110 !
b1100110 '
b1100110 $
b1100110 &
#361
b1101000 *
b1100111 !
b1100111 '
b1100111 $
b1100111 &
#362
b1101001 *
b1101000 !
b1101000 '
b1101000 $
b1101000 &
#363
b1101010 *
b1101001 !
b1101001 '
b1101001 $
b1101001 &
#364
b1101011 *
b1101010 !
b1101010 '
b1101010 $
b1101010 &
#365
b1101100 *
b1101011 !
b1101011 '
b1101011 $
b1101011 &
#366
b1101101 *
b1101100 !
b1101100 '
b1101100 $
b1101100 &
#367
b1101110 *
b1101101 !
b1101101 '
b1101101 $
b1101101 &
#368
b1101111 *
b1101110 !
b1101110 '
b1101110 $
b1101110 &
#369
b1110000 *
b1101111 !
b1101111 '
b1101111 $
b1101111 &
#370
b1110001 *
b1110000 !
b1110000 '
b1110000 $
b1110000 &
#371
b1110010 *
b1110001 !
b1110001 '
b1110001 $
b1110001 &
#372
b1110011 *
b1110010 !
b1110010 '
b1110010 $
b1110010 &
#373
b1110100 *
b1110011 !
b1110011 '
b1110011 $
b1110011 &
#374
b1110101 *
b1110100 !
b1110100 '
b1110100 $
b1110100 &
#375
b1110110 *
b1110101 !
b1110101 '
b1110101 $
b1110101 &
#376
b1110111 *
b1110110 !
b1110110 '
b1110110 $
b1110110 &
#377
b1111000 *
b1110111 !
b1110111 '
b1110111 $
b1110111 &
#378
b1111001 *
b1111000 !
b1111000 '
b1111000 $
b1111000 &
#379
b1111010 *
b1111001 !
b1111001 '
b1111001 $
b1111001 &
#380
b1111011 *
b1111010 !
b1111010 '
b1111010 $
b1111010 &
#381
b1111100 *
b1111011 !
b1111011 '
b1111011 $
b1111011 &
#382
b1111101 *
b1111100 !
b1111100 '
b1111100 $
b1111100 &
#383
b1111110 *
b1111101 !
b1111101 '
b1111101 $
b1111101 &
#384
b1111111 *
b1111110 !
b1111110 '
b1111110 $
b1111110 &
#385
b10000000 *
b1111111 !
b1111111 '
b1111111 $
b1111111 &
#386
b10000001 *
b10000000 !
b10000000 '
b10000000 $
b10000000 &
#387
b10000010 *
b10000001 !
b10000001 '
b10000001 $
b10000001 &
#388
b10000011 *
b10000010 !
b10000010 '
b10000010 $
b10000010 &
#389
b10000100 *
b10000011 !
b10000011 '
b10000011 $
b10000011 &
#390
b10000101 *
b10000100 !
b10000100 '
b10000100 $
b10000100 &
#391
b10000110 *
b10000101 !
b10000101 '
b10000101 $
b10000101 &
